Workbook

Sheet 1
A1: Предприятие выпускает два вида изделий: валы и зубчатые колеса. При изготовлении каждого изделия необходима обработка на трех станках: токарном, фрезерном и сверлильном. Токарный станок может использоваться не более 10 часов в сутки, фрезерный - не более 8, сверлильный - не более 10 часов. Прибыль от продажи одного вала составляет 4 ден.ед., от одного зубчатого колеса - 5 ден.ед. Затраты времени на выпуск изделий на каждом из станков приведены в таблице.
A12: Станки | B12: Затраты времени на выпуск одного изделия, мин | E12: Станки | F12: Время исп., не более мин в сутки | H12: Вид изделия | I12: Прибыль, ден.ед.
B13: Вал | C13: Зубчатое колесо
A14: Токарный | B14: 12 | C14: 5 | E14: Токарный | F14: 600 | H14: Вал | I14: 4
A15: Фрезерный | B15: 6 | C15: 11 | E15: Фрезерный | F15: 480 | H15: Зубчатое колесо | I15: 5
A16: Сверлильный | B16: 10 | C16: 10 | E16: Сверлильный | F16: 600
A18: X1 | B18: Вал
A19: X2 | B19: Зубчатое колесо | F19: X2
A21: Математическая модель
A22: Токарный | B22: 12*X1+5*X2<=600 | C22: Ограничения
A23: Фрезерный | B23: 6*X1+11*X2<=480
A24: Сверлильный | B24: 10*X1+10*X2<=600
B25: X1>=0
B26: X2>=0
A27: E= | B27: 4X1+5X2->max | C27: Целевая функция
A30: E(E)= | B30: =$I$14*0+$I$15*0 -> 0 | N30: Таким образом, точка В является оптимальным решением задачи: ни в одной из смежных с ней угловых точек ОДР (т.е. в точках А и С) значение це- левой функции по сравнению с точкой В не улучшается. Оптимальные значе- ния переменных (координаты точки В) следующие: X1=36, Х2=24. Это означает, что требуется выпускать за смену 4 корпуса и 24 задвижки. Прибыль при этом составит Е(В) = 4*36+5*24 = 264 ден. ед.
A31: E(A)= | B31: =$I$14*0+$I$15*43.63636 -> 218.1818
A32: E(B)= | B32: =$I$14*36+$I$15*24 -> 264
A33: E(C)= | B33: =$I$14*42.85714+$I$15*17.14286 -> 257.14286
A34: E(D)= | B34: =$I$14*50+$I$15*0 -> 200 | L34: X1
A38: Симплекс-метод
A40: Стандартная форма математической модели
A41: Токарный | B41: 12*X1+5*X2+X3= | C41: 600
A42: Фрезерный | B42: 6*X1+11*X2+X4= | C42: 480
A43: Сверлильный | B43: 10*X1+10*X2+X5= | C43: 600
B44: >=0; j=1,…,5
A45: E= | B45: 4X1+5X2->max
A47: Базисные переменные | D47: Не базисные переменные
A48: X3= | B48: 600 | D48: X1= | E48: 0
A49: X4= | B49: 480 | D49: X2= | E49: 0
A50: X5= | B50: 600
A53: Базис | B53: Х1 | C53: Х2 | D53: Х3 | E53: Х4 | F53: Х5 | G53: Решение | I53: Это решение является допустимым, так как значения X1=X2=0 соответствуют системе ограничений. Таким образом, в качестве начальной угловой точки ОДР выбрано начало координат. Выбранное решение явно не является оптимальным, так как целевая функция Е = 4Х1+5Х2 при этом равна нулю. По своему смыслу это решение означает, что никакие изделия не выпускаются.
A54: Е | B54: -4 | C54: -5 | D54: 0 | E54: 0 | F54: 0 | G54: 0
A55: Х3 | B55: 12 | C55: 5 | D55: 1 | E55: 0 | F55: 0 | G55: 600
A56: Х4 | B56: 6 | C56: 11 | D56: 0 | E56: 1 | F56: 0 | G56: 480
A57: Х5 | B57: 10 | C57: 10 | D57: 0 | E57: 0 | F57: 1 | G57: 600
B59: Симплексные отношения | F59: x1=0
B60: Х3: 600/5= | C60: =G55/C55 -> 120 | F60: x2=0
B61: Х4: 480/11= | C61: =G56/C56 -> 43.636364 | D61: (минимальное) | F61: x3=600
B62: Х5: 600/10= | C62: =G57/C57 -> 60 | F62: x4=480
F63: x5=600
F64: E=0
A65: Базис | B65: Х1 | C65: Х2 | D65: Х3 | E65: Х4 | F65: Х5 | G65: Решение
A66: Е | B66: =(C56*B54-C54*B56)/C56 -> -1.2727273 | C66: 0 | D66: 0 | E66: =(C56*E54-C54*E56)/C56 -> 0.45454545 | F66: 0 | G66: =(C56*G54-C54*G56)/C56 -> 218.18182
A67: Х3 | B67: =(C56*B55-B56*C55)/C56 -> 9.2727273 | C67: 0 | D67: 1 | E67: =(C56*E55-C55*E56)/C56 -> -0.45454545 | F67: 0 | G67: =(C56*G55-C55*G56)/C56 -> 381.81818
A68: Х2 | B68: =B56/C56 -> 0.54545455 | C68: =C56/C56 -> 1 | D68: 0 | E68: =E56/C56 -> 0.090909091 | F68: 0 | G68: =G56/C56 -> 43.636364
A69: Х5 | B69: =(C56*B57-B56*C57)/C56 -> 4.5454545 | C69: 0 | D69: 0 | E69: =(C56*E57-C57*E56)/C56 -> -0.90909091 | F69: 1 | G69: =(C56*G57-C57*G56)/C56 -> 163.63636
B71: Симплексные отношения | F71: x1=0
B72: Х3: 382/9,27= | C72: =G67/B67 -> 41.176471 | F72: x2=44
B73: Х2: 44/0,55= | C73: =G68/B68 -> 80 | F73: x3=382
B74: Х5: 164/4,55= | C74: =G69/B69 -> 36 | D74: (минимальное) | F74: x4=0
F75: x5=164
F76: E=218
A77: Базис | B77: Х1 | C77: Х2 | D77: Х3 | E77: Х4 | F77: Х5 | G77: Решение
A78: Е | B78: 0 | C78: 0 | D78: 0 | E78: =(B69*E66-B66*E69)/B69 -> 0.2 | F78: =(B69*F66-B66*F69)/B69 -> 0.28 | G78: =(B69*G66-B66*G69)/B69 -> 264
A79: Х3 | B79: 0 | C79: 0 | D79: 1 | E79: =(B69*E67-B67*E69)/B69 -> 1.4 | F79: =(B69*F67-B67*F69)/B69 -> -2.04 | G79: =(B69*G67-B67*G69)/B69 -> 48
A80: Х2 | B80: 0 | C80: =C68/C68 -> 1 | D80: 0 | E80: =(B69*E68-B68*E69)/B69 -> 0.2 | F80: =(B69*F68-B68*F69)/B69 -> -0.12 | G80: =(B69*G68-B68*G69)/B69 -> 24
A81: Х1 | B81: =B69/B69 -> 1 | C81: =C69/B69 -> 0 | D81: 0 | E81: =E69/B69 -> -0.2 | F81: =F69/B69 -> 0.22 | G81: =G69/B69 -> 36
I82: Решение оптимально, так как в Е-строке нет отрицательных элементов.
F83: x1=36 | I83: Полученное решение соответствует угловой точке ОДР, обозначенной на графике как В (X1=36; Х2=24).
B84: E=264 | F84: x2=24
B85: X1=36 | F85: x3=48
B86: X2=24 | F86: x4=0
B87: X3=48 | F87: x5=0
B88: X4=0 | F88: E=264
B89: X5=0
C93: Х1 | D93: Х2
B94: Решение | C94: 36 | D94: 24
B95: Целевая функция | C95: 4 | D95: 5 | E95: =SUMPRODUCT(C95:D95,C94:D94) -> 264 | F95: –> | G95: max
B96: Ограничения | C96: 12 | D96: 5 | E96: =SUMPRODUCT(C96:D96,C94:D94) -> 552 | F96: <= | G96: 600
C97: 6 | D97: 11 | E97: =SUMPRODUCT(C97:D97,C94:D94) -> 480 | F97: <= | G97: 480
C98: 10 | D98: 10 | E98: =SUMPRODUCT(C98:D98,C94:D94) -> 600 | F98: <= | G98: 600
A101: Анализ на чувствительность
A103: к изменению максимального времени работы сверлильного станка | N103: к изменению максимального времени работы фрезерного станка
O105: Диапазон для x4 | P105: новый ресурс | Q105: 670
B106: Диапазон для x5 | C106: новый ресурс | D106: 640 | R106: d= | S106: =Q105-480 -> 190
C107: d= | D107: =D106-600 -> 40 | O107: X1=36-0,2d>=0
B108: X1=36+0,22d>=0 | O108: X2=24+0,2d>=0 | R108: E=264+0,2d= | S108: =G78+E78*S106 -> 302
B109: X2=24-0,12d>=0 | C109: E=264+0,28d= | D109: =G78+F78*D107 -> 275.2 | O109: X3=48+1,4d>=0 | R109: X1=36-0,2d= | S109: =G81+E81*S106 -> -2
B110: X3=48-2,04d>=0 | C110: X1=36+0,22d= | D110: =G81+F81*D107 -> 44.8 | O110: .-34,3<=d<=180 | R110: X2=24+0,2d= | S110: =G80+E80*S106 -> 62
B111: .-163,8<=d<=23,4 | C111: X2=24-0,12d= | D111: =G80+F80*D107 -> 19.2 | R111: X3=48+1,4d= | S111: =G79+E79*S106 -> 314
C112: X3=48-2,04d= | D112: =G79+F79*D107 -> -33.6
P113: Диапазон ресурса | Q113: от | R113: =480-34.3 -> 445.7
C114: Диапазон ресурса | D114: от | E114: =600-163.8 -> 436.2 | Q114: до | R114: =480+180 -> 660
D115: до | E115: =600+23.4 -> 623.4
M119: к изменению прибыли от выпуска одного зубчатого колеса
A120: к изменению прибыли от выпуска одного вала
C122: 7 | N122: d= | O122: 5
B123: d= | C123: 4
N124: F4=0,2+0,2d= | O124: =0.2+0.2*O122 -> 1.2 | Q124: F4=0,2+0,2d>=0
B125: F4=0,2-0,2d= | C125: =0.2-0.2*C123 -> -0.6 | E125: F4=0,2-0,2d>=0 | N125: F5=0,28-0,12d= | O125: =0.28-0.12*O122 -> -0.32 | Q125: F5=0,28-0,12d>=0
B126: F5=0,28+0,22d= | C126: =0.28+0.22*C123 -> 1.16 | E126: F5=0,28+0,22d>=0 | N126: E=264+24d= | O126: =264+24*O122 -> 384 | Q126: .-1<=d<=2,33
B127: E=264+36d= | C127: =264+36*C123 -> 408 | E127: .-1,27<=d<=1 | Q127: Диапазон прибыли | S127: от | T127: =-1+5 -> 4
E128: Диапазон прибыли | G128: от | H128: =-1.27+4 -> 2.73 | S128: до | T128: =2.33+5 -> 7.33
G129: до | H129: =1+4 -> 5
C133: Найденное для задачи решение (Х1=36; X1=24; Хз=48; Х4=0; Х5=0) оптимально, если прибыль от выпуска одного корпуса будет составлять от 5-1 до 5+2,33 ден.ед., т.е. от 4 до 7,33 ден.ед. Если коэффициент целевой функции выходит за найденный диапазон, то для получения оптимального решения необходимо решить задачу заново (с новой целевой функцией), используя симплекс-метод. Новое оптимальное решение будет отличаться от прежнего не только значениями, но и составом переменных в оптимальном базисе. При этом прежнее решение (т.е. оптимальное решение исходной задачи) уже не будет оптимальным, но останется допустимым, так как оно удовлетворяет ограничениям задачи.

Sheet 2
A1: Вид продукции, тонн | B1: Цена, тыс.д.е. | C1: Руда, тонн | D1: Опасные отходы | E1: Выпуск | F1: Доп условие
A2: Серная кислота | B2: 3 | C2: 12.5 | D2: 100 | E2: ≥200 | F2: 1
A3: Хлорпикриновая кислота | B3: 4 | C3: 6 | D3: 250 | F3: 2
B4: ≥1500 | C4: ≤5000
A7: Двухэтапный метод
A9: Серная кислота | B9: Х1 | D9: Математическая модель | G9: Стандартная форма
A10: Хлорпикриновая кислота | B10: Х2 | D10: Х1≥200 | G10: Х1-Х3=200
D11: 3Х1+4Х2≥1500 | G11: 3Х1+4Х2-Х4=1500
D12: 12,5*Х1+6*X2≤5000 | G12: 12,5*Х1+6*X2+X5=5000
D13: E=100*Х1+250*Х2->min | G13: Хi≥0, i=1,…,5
G14: -E=-100*Х1-250*Х2->max
A16: Первый этап (поиск допустимого решения)
A18: Х1-Х3+Х6=200 | D18: X6=200-X1+X3
A19: 3Х1+4Х2-Х4+Х7=1500 | D19: X7=1500-3X1-4X2+X4
A20: 12,5Х1+6X2+X5=5000 | D20: W=200-X1+X3+1500-3X1-4X2+X4->min
A21: Хi≥0, i=1,…,7 | D21: -W=-1700+4X1+4X2-X3-X4->max
A22: -E=-100*Х1-250*Х2->max
A23: W=Х6+Х7->min
A25: Полная математическая модель | E25: Базисные переменные | H25: Небазисные переменные
A26: Х1-Х3+Х6=200 | E26: Х5 | F26: 5000 | H26: Х1 | I26: 0
A27: 3Х1+4Х2-Х4+Х7=1500 | E27: Х6 | F27: 200 | H27: Х2 | I27: 0
A28: 12,5Х1+6X2+X5=5000 | E28: Х7 | F28: 1500 | H28: Х3 | I28: 0
A29: Хi≥0, i=1,…,7 | H29: Х4 | I29: 0
A30: -E=-100*Х1-250*Х2->max
A31: -W=4X1+4X2-X3-X4-1700->max
A33: Начальное значение целевой функции = 0, искусственной целевой функции = -1700
A35: Исходная Симплекс-таблица
A36: Базис | B36: Х1 | C36: Х2 | D36: Х3 | E36: Х4 | F36: Х5 | G36: Х6 | H36: Х7 | I36: Решение
A37: -E | B37: 100 | C37: 250 | D37: 0 | E37: 0 | F37: 0 | G37: 0 | H37: 0 | I37: 0
A38: -W | B38: -4 | C38: -4 | D38: 1 | E38: 1 | F38: 0 | G38: 0 | H38: 0 | I38: -1700
A39: X5 | B39: 12.5 | C39: 6 | D39: 0 | E39: 0 | F39: 1 | G39: 0 | H39: 0 | I39: 5000
A40: X6 | B40: 1 | C40: 0 | D40: -1 | E40: 0 | F40: 0 | G40: 1 | H40: 0 | I40: 200
A41: X7 | B41: 3 | C41: 4 | D41: 0 | E41: -1 | F41: 0 | G41: 0 | H41: 1 | I41: 1500
A43: Симплекс отношения
A44: X5 | B44: =I39/B39 -> 400
A45: X6 | B45: =I40/B40 -> 200
A46: X7 | B46: =I41/B41 -> 500
A48: Базис | B48: Х1 | C48: Х2 | D48: Х3 | E48: Х4 | F48: Х5 | G48: Х6 | H48: Х7 | I48: Решение
A49: -E | B49: 0 | C49: =(B40*C37-B37*C40)/B40 -> 250 | D49: =(B40*D37-B37*D40)/B40 -> 100 | E49: =($B$40*E37-$B$37*E40)/$B$40 -> 0 | F49: =($B$40*F37-$B$37*F40)/$B$40 -> 0 | G49: =($B$40*G37-$B$37*G40)/$B$40 -> -100 | H49: =($B$40*H37-$B$37*H40)/$B$40 -> 0 | I49: =($B$40*I37-$B$37*I40)/$B$40 -> -20000
A50: -W | B50: 0 | C50: =(B40*C38-B38*C40)/B40 -> -4 | D50: =(B40*D38-B38*D40)/B40 -> -3 | E50: =($B$40*E38-$B$38*E40)/$B$40 -> 1 | F50: =($B$40*F38-$B$38*F40)/$B$40 -> 0 | G50: =($B$40*G38-$B$38*G40)/$B$40 -> 4 | H50: =($B$40*H38-$B$38*H40)/$B$40 -> 0 | I50: =($B$40*I38-$B$38*I40)/$B$40 -> -900
A51: X5 | B51: 0 | C51: =(B40*C39-B39*C40)/B40 -> 6 | D51: =(B40*D39-B39*D40)/B40 -> 12.5 | E51: =($B$40*E39-$B$39*E40)/$B$40 -> 0 | F51: =($B$40*F39-$B$39*F40)/$B$40 -> 1 | G51: =($B$40*G39-$B$39*G40)/$B$40 -> -12.5 | H51: =($B$40*H39-$B$39*H40)/$B$40 -> 0 | I51: =($B$40*I39-$B$39*I40)/$B$40 -> 2500
A52: X1 | B52: =B40/B40 -> 1 | C52: =C40/B40 -> 0 | D52: =D40/B40 -> -1 | E52: =E40/$B$40 -> 0 | F52: =F40/$B$40 -> 0 | G52: =G40/$B$40 -> 1 | H52: =H40/$B$40 -> 0 | I52: =I40/$B$40 -> 200
A53: X7 | B53: 0 | C53: =(B40*C41-B41*C40)/B40 -> 4 | D53: =(B40*D41-B41*D40)/B40 -> 3 | E53: =($B$40*E41-$B$41*E40)/$B$40 -> -1 | F53: =($B$40*F41-$B$41*F40)/$B$40 -> 0 | G53: =($B$40*G41-$B$41*G40)/$B$40 -> -3 | H53: =($B$40*H41-$B$41*H40)/$B$40 -> 1 | I53: =($B$40*I41-$B$41*I40)/$B$40 -> 900
A55: Симплекс отношения
A56: X5 | B56: =I51/C51 -> 416.66667
A57: X7 | B57: =I53/C53 -> 225
A59: Базис | B59: Х1 | C59: Х2 | D59: Х3 | E59: Х4 | F59: Х5 | G59: Х6 | H59: Х7 | I59: Решение
A60: -E | B60: =($C$53*B49-$C$49*B53)/$C$53 -> 0 | C60: 0 | D60: =($C$53*D49-$C$49*D53)/$C$53 -> -87.5 | E60: =($C$53*E49-$C$49*E53)/$C$53 -> 62.5 | F60: =($C$53*F49-$C$49*F53)/$C$53 -> 0 | G60: =($C$53*G49-$C$49*G53)/$C$53 -> 87.5 | H60: =($C$53*H49-$C$49*H53)/$C$53 -> -62.5 | I60: =($C$53*I49-$C$49*I53)/$C$53 -> -76250
A61: -W | B61: =($C$53*B50-C50*$B$53)/$C$53 -> 0 | C61: 0 | D61: =($C$53*D50-$C$50*D53)/$C$53 -> 0 | E61: =($C$53*E50-$C$50*E53)/$C$53 -> 0 | F61: =($C$53*F50-$C$50*F53)/$C$53 -> 0 | G61: =($C$53*G50-$C$50*G53)/$C$53 -> 1 | H61: =($C$53*H50-$C$50*H53)/$C$53 -> 1 | I61: =($C$53*I50-$C$50*I53)/$C$53 -> 0
A62: X5 | B62: =($C$53*B51-C51*$B$53)/$C$53 -> 0 | C62: 0 | D62: =($C$53*D51-$C$51*D53)/$C$53 -> 8 | E62: =($C$53*E51-$C$51*E53)/$C$53 -> 1.5 | F62: =($C$53*F51-$C$51*F53)/$C$53 -> 1 | G62: =($C$53*G51-$C$51*G53)/$C$53 -> -8 | H62: =($C$53*H51-$C$51*H53)/$C$53 -> -1.5 | I62: =($C$53*I51-$C$51*I53)/$C$53 -> 1150
A63: X1 | B63: =($C$53*B52-C52*$B$53)/$C$53 -> 1 | C63: 0 | D63: =($C$53*D52-$C$52*D53)/$C$53 -> -1 | E63: =($C$53*E52-$C$52*E53)/$C$53 -> 0 | F63: =($C$53*F52-$C$52*F53)/$C$53 -> 0 | G63: =($C$53*G52-$C$52*G53)/$C$53 -> 1 | H63: =($C$53*H52-$C$52*H53)/$C$53 -> 0 | I63: =($C$53*I52-$C$52*I53)/$C$53 -> 200
A64: X2 | B64: =B53/$C$53 -> 0 | C64: =C53/$C$53 -> 1 | D64: =D53/$C$53 -> 0.75 | E64: =E53/$C$53 -> -0.25 | F64: =F53/$C$53 -> 0 | G64: =G53/$C$53 -> -0.75 | H64: =H53/$C$53 -> 0.25 | I64: =I53/$C$53 -> 225
A66: Как видно из таблицы, искусственная целевая функция равна нулю, и все искусственные переменные исключены из базиса. Получено допустимое решение. Таким образом, первый этап двухэтапного метода завершен. Искусственная целевая функция и искусственные переменные исключаются из симплекс-таблицы
A71: Базис | B71: Х1 | C71: Х2 | D71: Х3 | E71: Х4 | F71: Х5 | G71: Решение
A72: -E | B72: 0 | C72: 0 | D72: -87.5 | E72: 62.5 | F72: 0 | G72: -76250
A73: X5 | B73: 0 | C73: 0 | D73: 8 | E73: 1.5 | F73: 1 | G73: 1150
A74: X1 | B74: 1 | C74: 0 | D74: -1 | E74: 0 | F74: 0 | G74: 200
A75: X2 | B75: 0 | C75: 1 | D75: 0.75 | E75: -0.25 | F75: 0 | G75: 225
A77: Второй этап (поиск оптимального решения)
A79: Базис | B79: Х1 | C79: Х2 | D79: Х3 | E79: Х4 | F79: Х5 | G79: Решение
A80: -E | B80: 0 | C80: 0 | D80: -87.5 | E80: 62.5 | F80: 0 | G80: -76250
A81: X5 | B81: 0 | C81: 0 | D81: 8 | E81: 1.5 | F81: 1 | G81: 1150
A82: X1 | B82: 1 | C82: 0 | D82: -1 | E82: 0 | F82: 0 | G82: 200
A83: X2 | B83: 0 | C83: 1 | D83: 0.75 | E83: -0.25 | F83: 0 | G83: 225
A85: Симплекс отношения
A86: X5 | B86: =G81/D81 -> 143.75
A87: X2 | B87: =G83/D83 -> 300
A89: Базис | B89: Х1 | C89: Х2 | D89: Х3 | E89: Х4 | F89: Х5 | G89: Решение
A90: -E | B90: =(D81*B80-D80*B81)/D81 -> 0 | C90: =(D81*C80-D80*C81)/D81 -> 0 | D90: 0 | E90: =(D81*E80-D80*E81)/D81 -> 78.90625 | F90: =(D81*F80-D80*F81)/D81 -> 10.9375 | G90: =(D81*G80-D80*G81)/D81 -> -63671.875
A91: X3 | B91: =B81/$D$81 -> 0 | C91: =C81/$D$81 -> 0 | D91: =D81/$D$81 -> 1 | E91: =E81/$D$81 -> 0.1875 | F91: =F81/$D$81 -> 0.125 | G91: =G81/$D$81 -> 143.75
A92: X1 | B92: =(D81*B82-B81*D82)/D81 -> 1 | C92: =(D81*C82-C81*D82)/D81 -> 0 | D92: 0 | E92: =(D81*E82-E81*D82)/D81 -> 0.1875 | F92: =(D81*F82-F81*D82)/D81 -> 0.125 | G92: =(D81*G82-G81*D82)/D81 -> 343.75
A93: X2 | B93: =(D81*B83-B81*D83)/D81 -> 0 | C93: =(D82*C83-C82*D83)/D82 -> 1 | D93: 0 | E93: =(D81*E83-E81*D83)/D81 -> -0.390625 | F93: =(D81*F83-F81*D83)/D81 -> -0.09375 | G93: =(D81*G83-G81*D83)/D81 -> 117.1875
A96: Оптимальное решение. Х1 = 343,75; Х2 = 117,188
A98: Выбросы: 63671,875 кг.
A99: Остаток серной кислоты: 143,75 т.
A101: Доп.условие
A103: Математическая модель | D103: Стандартная форма
A104: Х1≥200 | D104: Х1-Х3=200
A105: 3Х1+4Х2≥1500 | D105: 3Х1+4Х2-Х4=1500
A106: 2X1-X2=0 | D106: 2X1-X2=0
A107: 12,5*Х1+6*X2≤5000 | D107: 12,5*Х1+6*X2+X5=5000
A108: E=100*Х1+250*Х2->min | D108: Хi≥0, i=1,…,5
D109: -E=-100*Х1-250*Х2->max
A111: Х1-Х3+Х6=200 | D111: X6=200-X1+X3
A112: 2X1-X2+X8=0 | D112: X8=X2-2X1
A113: 3Х1+4Х2-Х4+Х7=1500 | D113: X7=1500-3X1-4X2+X4
A114: 12,5Х1+6X2+X5=5000 | D114: W=200-X1+X3+1500-3X1-4X2+X4+X2-2X1->min
A115: Хi≥0, i=1,…,8 | D115: -W=-1700+6X1+3X2-X3-X4->max
A116: -E=-100*Х1-250*Х2->max
A117: W=Х6+Х7+X8->min
A119: Полная математическая модель | E119: Базисные переменные | H119: Небазисные переменные
A120: Х1-Х3+Х6=200 | E120: Х5 | F120: 5000 | H120: Х1 | I120: 0
A121: 3Х1+4Х2-Х4+Х7=1500 | E121: Х6 | F121: 200 | H121: Х2 | I121: 0
A122: 2X1-X2+X8=0 | E122: Х7 | F122: 1500 | H122: Х3 | I122: 0
A123: 12,5Х1+6X2+X5=5000 | E123: Х8 | F123: 0 | H123: Х4 | I123: 0
A124: Хi≥0, i=1,…,8
A125: -E=-100*Х1-250*Х2->max
A126: -W=-1700+6X1+3X2-X3-X4->max
A128: Начальное значение целевой функции = 0, искусственной целевой функции = -1700
A130: Исходная Симплекс-таблица
...

Sheet 3
A1: Материал | B1: Запас материала, кг | C1: Расход на одно изделие, кг
C2: И1 | D2: И2
A3: Пластмасса | B3: 120 | C3: 4 | D3: 7
A4: Алюминий | B4: 100 | C4: 6 | D4: 4
A5: Прибыль, ден.ед. | C5: 200 | D5: 300
A7: Х1 | B7: Кол-во И1
A8: Х2 | B8: Кол-во И2
A10: Математическая модель | D10: Стандартная форма | G10: Остаточные переменные Х3, Х4 обозначают, соответсвенно, неизвестный остаток пластмассы и алюминия в килограммах. Эти переменные могут принимать как целые, так и дробные значения. Таким образом, задача является частично целочисленной
A11: 4Х1+7Х2≤120 | D11: 4Х1+7Х2+Х3=120
A12: 6Х1+4Х1≤100 | D12: 6Х1+4Х1+Х4=100
A13: X1 ≥ 0,X2 ≥ 0 | D13: Xi ≥ 0, i=1,…,4
A14: Х1, Х2 ─ целые | D14: Х1, Х2 ─ целые
A15: Е=200Х1+300Х2 → max | D15: Е=200Х1+300Х2 → max
A17: 1)
B18: X1 | C18: X2
A19: Решение | B19: 8.4615385 | C19: 12.307692 | O19: 1
A20: Целевая функция | B20: 200 | C20: 300 | D20: =SUMPRODUCT(B20:C20,B19:C19) -> 5384.6154 | E20: → | F20: max | O20: 4Х1+7Х2≤120
A21: Ограничения | B21: 4 | C21: 7 | D21: =SUMPRODUCT(B21:C21,B19:C19) -> 120 | E21: ≤ | F21: 120 | O21: 6Х1+4Х1≤100
B22: 6 | C22: 4 | D22: =SUMPRODUCT(B22:C22,B19:C19) -> 100 | E22: ≤ | F22: 100 | O22: Е=200Х1+300Х2 → max
O23: X1=8,46 | P23: X2=12,31
A24: 2) | O24: E= | P24: =D20 -> 5384.6154
B25: X1 | C25: X2 | K25: 2 | S25: 3
A26: Решение | B26: 8 | C26: 12.571429 | K26: 4Х1+7Х2≤120 | S26: 4Х1+7Х2≤120
A27: Целевая функция | B27: 200 | C27: 300 | D27: =SUMPRODUCT(B27:C27,B26:C26) -> 5371.4286 | E27: → | F27: max | K27: 6Х1+4Х1≤100 | S27: 6Х1+4Х1≤100
A28: Ограничения | B28: 4 | C28: 7 | D28: =SUMPRODUCT(B28:C28,B26:C26) -> 120 | E28: ≤ | F28: 120 | K28: X1 ≤ 8 | S28: X1 ≥ 9
B29: 6 | C29: 4 | D29: =SUMPRODUCT(B29:C29,B26:C26) -> 98.285714 | E29: ≤ | F29: 100 | K29: Е=200Х1+300Х2 → max | S29: Е=200Х1+300Х2 → max
B30: 1 | C30: 0 | D30: =SUMPRODUCT(B26:C26,B30:C30) -> 8 | E30: ≤ | F30: 8 | K30: X1=8 | L30: X2=12,57 | S30: X1=9 | T30: X2=11,25
K31: E= | L31: =D27 -> 5371.4286 | S31: E= | T31: =D35 -> 5250
A32: 3)
B33: X1 | C33: X2 | I33: 4 | M33: 5 | Q33: 6 | U33: 7
A34: Решение | B34: 9 | C34: 11.5 | I34: 4Х1+7Х2≤120 | M34: 4Х1+7Х2≤120 | Q34: 4Х1+7Х2≤120 | U34: 4Х1+7Х2≤120
A35: Целевая функция | B35: 200 | C35: 300 | D35: =SUMPRODUCT(B35:C35,B34:C34) -> 5250 | E35: → | F35: max | I35: 6Х1+4Х1≤100 | M35: 6Х1+4Х1≤100 | Q35: 6Х1+4Х1≤100 | U35: 6Х1+4Х1≤100
A36: Ограничения | B36: 4 | C36: 7 | D36: =SUMPRODUCT(B36:C36,B34:C34) -> 116.5 | E36: ≤ | F36: 120 | I36: X1 ≤ 8, Х2 ≤ 12 | M36: X1 ≤ 8, Х2 ≥13 | Q36: X1 ≥ 9, Х2 ≤ 11 | U36: X1 ≥ 9, Х2 ≥ 12
B37: 6 | C37: 4 | D37: =SUMPRODUCT(B37:C37,B34:C34) -> 100 | E37: ≤ | F37: 100 | I37: Е=200Х1+300Х2 → max | M37: Е=200Х1+300Х2 → max | Q37: Е=200Х1+300Х2 → max | U37: Е=200Х1+300Х2 → max
B38: 1 | C38: 0 | D38: =SUMPRODUCT(B34:C34,B38:C38) -> 9 | E38: ≥ | F38: 9 | I38: X1=8 | J38: X2=12 | M38: X1=7,25 | N38: X2=13 | Q38: X1=9,33 | R38: X2=11 | U38: Нет решения
I39: E= | J39: =D43 -> 5200 | M39: E= | N39: =D52 -> 5350 | Q39: E= | R39: =D61 -> 5166.6667
A40: 4)
B41: X1 | C41: X2 | K41: 8 | O41: 9
A42: Решение | B42: 8 | C42: 12 | K42: 4Х1+7Х2≤120 | O42: 4Х1+7Х2≤120
A43: Целевая функция | B43: 200 | C43: 300 | D43: =SUMPRODUCT(B43:C43,B42:C42) -> 5200 | E43: → | F43: max | K43: 6Х1+4Х1≤100 | O43: 6Х1+4Х1≤100
A44: Ограничения | B44: 4 | C44: 7 | D44: =SUMPRODUCT(B44:C44,B42:C42) -> 116 | E44: ≤ | F44: 120 | K44: X1 ≤ 8, Х2 ≥13, Х1 ≤ 7 | O44: X1 ≤ 8, Х2 ≥13, Х1 ≥ 8
B45: 6 | C45: 4 | D45: =SUMPRODUCT(B45:C45,B42:C42) -> 96 | E45: ≤ | F45: 100 | K45: Е=200Х1+300Х2 → max | O45: Е=200Х1+300Х2 → max
B46: 1 | C46: 0 | D46: =SUMPRODUCT(B42:C42,B46:C46) -> 8 | E46: ≤ | F46: 8 | K46: X1=7 | L46: X2=13,14 | O46: Нет решения
B47: 0 | C47: 1 | D47: =SUMPRODUCT(B42:C42,B47:C47) -> 12 | E47: ≤ | F47: 12 | K47: E= | L47: =D79 -> 5342.8571
A49: 5) | I49: 10 | M49: 11
B50: X1 | C50: X2 | I50: 4Х1+7Х2≤120 | M50: 4Х1+7Х2≤120
A51: Решение | B51: 7.25 | C51: 13 | I51: 6Х1+4Х1≤100 | M51: 6Х1+4Х1≤100
A52: Целевая функция | B52: 200 | C52: 300 | D52: =SUMPRODUCT(B52:C52,B51:C51) -> 5350 | E52: → | F52: max | I52: X1 ≤ 8, Х2 ≥13, Х1 ≤ 7, Х2 ≤ 13 | M52: X1 ≤ 8, Х2 ≥13, Х1 ≤7, Х2≥14
A53: Ограничения | B53: 4 | C53: 7 | D53: =SUMPRODUCT(B53:C53,B51:C51) -> 120 | E53: ≤ | F53: 120 | I53: Е=200Х1+300Х2 → max | M53: Е=200Х1+300Х2 → max
B54: 6 | C54: 4 | D54: =SUMPRODUCT(B54:C54,B51:C51) -> 95.5 | E54: ≤ | F54: 100 | I54: X1=7 | J54: X2=13 | M54: X1=5,5 | N54: X2=14
B55: 1 | C55: 0 | D55: =SUMPRODUCT(B51:C51,B55:C55) -> 7.25 | E55: ≤ | F55: 8 | I55: E= | J55: =D100 -> 5300 | M55: E= | N55: =D111 -> 5300
B56: 0 | C56: 1 | D56: =SUMPRODUCT(B51:C51,B56:C56) -> 13 | E56: ≥ | F56: 13
A58: 6)
B59: X1 | C59: X2
A60: Решение | B60: 9.3333333 | C60: 11 | I60: Оптимальное решение Х1=7 Х2 =13. Прибыль составит 5300д.е. Можно также определить, что неизрасходованый остаток запаса пластмассы составит 1 кг, а алюминия - 6 кг
A61: Целевая функция | B61: 200 | C61: 300 | D61: =SUMPRODUCT(B61:C61,B60:C60) -> 5166.6667 | E61: → | F61: max
A62: Ограничения | B62: 4 | C62: 7 | D62: =SUMPRODUCT(B62:C62,B60:C60) -> 114.33333 | E62: ≤ | F62: 120
B63: 6 | C63: 4 | D63: =SUMPRODUCT(B63:C63,B60:C60) -> 100 | E63: ≤ | F63: 100
B64: 1 | C64: 0 | D64: =SUMPRODUCT(B60:C60,B64:C64) -> 9.3333333 | E64: ≥ | F64: 9
B65: 0 | C65: 1 | D65: =SUMPRODUCT(B60:C60,B65:C65) -> 11 | E65: ≤ | F65: 11
A67: 7)
B68: X1 | C68: X2
A69: Решение | B69: 9 | C69: 11.5
A70: Целевая функция | B70: 200 | C70: 300 | D70: =SUMPRODUCT(B70:C70,B69:C69) -> 5250 | E70: → | F70: max
A71: Ограничения | B71: 4 | C71: 7 | D71: =SUMPRODUCT(B71:C71,B69:C69) -> 116.5 | E71: ≤ | F71: 120
B72: 6 | C72: 4 | D72: =SUMPRODUCT(B72:C72,B69:C69) -> 100 | E72: ≤ | F72: 100
B73: 1 | C73: 0 | D73: =SUMPRODUCT(B69:C69,B73:C73) -> 9 | E73: ≥ | F73: 9
B74: 0 | C74: 1 | D74: =SUMPRODUCT(B69:C69,B74:C74) -> 11.5 | E74: ≥ | F74: 12
A76: 8)
B77: X1 | C77: X2
A78: Решение | B78: 7 | C78: 13.142857
A79: Целевая функция | B79: 200 | C79: 300 | D79: =SUMPRODUCT(B79:C79,B78:C78) -> 5342.8571 | E79: → | F79: max
A80: Ограничения | B80: 4 | C80: 7 | D80: =SUMPRODUCT(B80:C80,B78:C78) -> 120 | E80: ≤ | F80: 120
B81: 6 | C81: 4 | D81: =SUMPRODUCT(B81:C81,B78:C78) -> 94.571429 | E81: ≤ | F81: 100
B82: 1 | C82: 0 | D82: =SUMPRODUCT(B78:C78,B82:C82) -> 7 | E82: ≤ | F82: 8
B83: 0 | C83: 1 | D83: =SUMPRODUCT(B78:C78,B83:C83) -> 13.142857 | E83: ≥ | F83: 13
B84: 1 | C84: 0 | D84: =SUMPRODUCT(B78:C78,B84:C84) -> 7 | E84: ≤ | F84: 7
A86: 9)
B87: X1 | C87: X2
A88: Решение | B88: 8 | C88: 12.571429
A89: Целевая функция | B89: 200 | C89: 300 | D89: =SUMPRODUCT(B89:C89,B88:C88) -> 5371.4286 | E89: → | F89: max
A90: Ограничения | B90: 4 | C90: 7 | D90: =SUMPRODUCT(B90:C90,B88:C88) -> 120 | E90: ≤ | F90: 120
B91: 6 | C91: 4 | D91: =SUMPRODUCT(B91:C91,B88:C88) -> 98.285714 | E91: ≤ | F91: 100
B92: 1 | C92: 0 | D92: =SUMPRODUCT(B88:C88,B92:C92) -> 8 | E92: ≤ | F92: 8
B93: 0 | C93: 1 | D93: =SUMPRODUCT(B88:C88,B93:C93) -> 12.571429 | E93: ≥ | F93: 13
B94: 1 | C94: 0 | D94: =SUMPRODUCT(B88:C88,B94:C94) -> 8 | E94: ≥ | F94: 8
A97: 10)
B98: X1 | C98: X2
A99: Решение | B99: 7 | C99: 13
A100: Целевая функция | B100: 200 | C100: 300 | D100: =SUMPRODUCT(B100:C100,B99:C99) -> 5300 | E100: → | F100: max
A101: Ограничения | B101: 4 | C101: 7 | D101: =SUMPRODUCT(B101:C101,B99:C99) -> 119 | E101: ≤ | F101: 120
B102: 6 | C102: 4 | D102: =SUMPRODUCT(B102:C102,B99:C99) -> 94 | E102: ≤ | F102: 100
B103: 1 | C103: 0 | D103: =SUMPRODUCT(B99:C99,B103:C103) -> 7 | E103: ≤ | F103: 8
B104: 0 | C104: 1 | D104: =SUMPRODUCT(B99:C99,B104:C104) -> 13 | E104: ≥ | F104: 13
B105: 1 | C105: 0 | D105: =SUMPRODUCT(B99:C99,B105:C105) -> 7 | E105: ≤ | F105: 7
B106: 0 | C106: 1 | D106: =SUMPRODUCT(B99:C99,B106:C106) -> 13 | E106: ≤ | F106: 13
A108: 11)
B109: X1 | C109: X2
A110: Решение | B110: 5.5 | C110: 14
A111: Целевая функция | B111: 200 | C111: 300 | D111: =SUMPRODUCT(B111:C111,B110:C110) -> 5300 | E111: → | F111: max
...

Sheet 4
A1: Шахта | B1: Населенный пункт | F1: Месечная добыча, тыс. тонн | H1: Найти объемы перевозок с каждой шахты в каждый из населенных пунктов, при которых затраты на перевозки будут минимальными. Решить задачу при следующем изменении: добыча угля на шахте 3 составляет 80 тыс. тонн.
B2: 1 | C2: 2 | D2: 3 | E2: 4
A3: 1 | B3: 6 | C3: 2 | D3: 3 | E3: 5 | F3: 100
A4: 2 | B4: 1 | C4: 2 | D4: 5 | E4: 6 | F4: 150
A5: 3 | B5: 3 | C5: 10 | D5: 20 | E5: 4 | F5: 50
A6: Потребность, тыс. тонн | B6: 75 | C6: 80 | D6: 60 | E6: 85
A8: Для удовлетворения спроса всех населенных пунктов
A10: X11+X12+X13+X14=100000
A11: X21+X22+X23+X24=150000
A12: X31+X32+X33+X34=50000
A14: Ограничения по товару
A16: X11+X21+X31=75000
A17: X12+X22+X32=80000
A18: X13+X23+X33=60000
A19: X14+X24+X34=85000
A21: Xij ≥ 0, i = 1, …, 3, j = 1, …, 4
A23: Целевая функция
A24: E=6*X11+2*X12+3*X13+5*X14+1*X21+2*X22+5*X23+6*X24+3*X31+10*X32+20*X33+4*X34 -> min
A26: Метод минимального элемента
A28: Шахта | B28: Населенный пункт | I28: Шахта | J28: Населенный пункт
B29: 1 | C29: 2 | D29: 3 | E29: 4 | J29: 1 | K29: 2 | L29: 3 | M29: 4
A30: 1 | B30: 6 | C30: 2 | D30: 3 | E30: 5 | F30: 100 | I30: 1 | J30: 6 | K30: 2 | L30: 3 | M30: 5 | N30: 100
A31: 2 | B31: 1 | C31: 2 | D31: 5 | E31: 6 | F31: 150 | I31: 2 | J31: 75 1 | K31: 2 | L31: 5 | M31: 6 | N31: 150 | O31: 75
A32: 3 | B32: 3 | C32: 10 | D32: 20 | E32: 4 | F32: 50 | I32: 3 | J32: 3 | K32: 10 | L32: 20 | M32: 4 | N32: 50
B33: 75 | C33: 80 | D33: 60 | E33: 85 | J33: 75 | K33: 80 | L33: 60 | M33: 85
A37: Шахта | B37: Населенный пункт | I37: Шахта | J37: Населенный пункт
B38: 1 | C38: 2 | D38: 3 | E38: 4 | J38: 1 | K38: 2 | L38: 3 | M38: 4
A39: 1 | B39: 6 | C39: 2 | D39: 3 | E39: 5 | F39: 100 | I39: 1 | J39: 6 | K39: 5 2 | L39: 3 | M39: 5 | N39: 100 | O39: 95
A40: 2 | B40: 75 1 | C40: 75 2 | D40: 5 | E40: 6 | F40: 150 | G40: 75 | I40: 2 | J40: 75 1 | K40: 75 2 | L40: 5 | M40: 6 | N40: 150 | O40: 75
A41: 3 | B41: 3 | C41: 10 | D41: 20 | E41: 4 | F41: 50 | I41: 3 | J41: 3 | K41: 10 | L41: 20 | M41: 4 | N41: 50
B42: 75 | C42: 80 | D42: 60 | E42: 85 | J42: 75 | K42: 80 | L42: 60 | M42: 85
C43: 5 | K43: 5
A46: Шахта | B46: Населенный пункт | J46: Шахта | K46: Населенный пункт
B47: 1 | C47: 2 | D47: 3 | E47: 4 | K47: 1 | L47: 2 | M47: 3 | N47: 4
A48: 1 | B48: 6 | C48: 5 2 | D48: 60 3 | E48: 5 | F48: 100 | G48: 95 | H48: 35 | J48: 1 | K48: 6 | L48: 5 2 | M48: 60 3 | N48: 5 | O48: 100 | P48: 95 | Q48: 35
A49: 2 | B49: 75 1 | C49: 75 2 | D49: 5 | E49: 6 | F49: 150 | G49: 75 | J49: 2 | K49: 75 1 | L49: 75 2 | M49: 5 | N49: 6 | O49: 150 | P49: 75
A50: 3 | B50: 3 | C50: 10 | D50: 20 | E50: 4 | F50: 50 | J50: 3 | K50: 3 | L50: 10 | M50: 20 | N50: 50 4 | O50: 50
B51: 75 | C51: 80 | D51: 60 | E51: 85 | K51: 75 | L51: 80 | M51: 60 | N51: 85
C52: 5 | L52: 5 | N52: 35
I55: Базисные
A56: Шахта | B56: Населенный пункт | I56: X12= | J56: 5000 | L56: m=3
B57: 1 | C57: 2 | D57: 3 | E57: 4 | I57: X13= | J57: 60000 | L57: n=4
A58: 1 | B58: 6 | C58: 5 2 | D58: 60 3 | E58: 35 5 | F58: 100 | I58: X14= | J58: 35000 | L58: m+n-1=6
A59: 2 | B59: 75 1 | C59: 75 2 | D59: 5 | E59: 6 | F59: 150 | I59: X21= | J59: 75000
A60: 3 | B60: 3 | C60: 10 | D60: 20 | E60: 50 4 | F60: 50 | I60: X22= | J60: 75000
B61: 75 | C61: 80 | D61: 60 | E61: 85 | I61: X34= | J61: 50000
I62: E= | J62: =J56*2+J57*3+J58*5+J59+J60*2+J61*4 -> 790000
A65: Метод потенциалов
A67: m=3 | C67: U1+V2=2 | E67: Пусть U1= | F67: 0 | I67: Шахта | J67: Населенный пункт
A68: n=4 | C68: U1+V3=3 | E68: V2= | F68: 2 | J68: 1 | K68: 2 | L68: 3 | M68: 4
A69: m+n-1=6 | C69: U1+V4=5 | E69: V3= | F69: 3 | I69: 1 | J69: 6 | K69: 2 | L69: 3 | M69: 5
C70: U2+V1=1 | E70: V4= | F70: 5 | I70: 2 | J70: 1 | K70: 2 | L70: 5 | M70: 6
C71: U2+V2=2 | E71: U2= | F71: 0 | I71: 3 | J71: 3 | K71: 10 | L71: 20 | M71: 4
C72: U3+V4=4 | E72: V1= | F72: 1
E73: U3= | F73: -1 | I73: Оптимальный план
I74: Шахта | J74: Населенный пункт
A75: Сумма платежей псевдостоимости | D75: Разность стоимости и псевдостоимости | J75: 1 | K75: 2 | L75: 3 | M75: 4
I76: 1 | J76: 0 | K76: 5 | L76: 60 | M76: 35 | N76: =SUM(J76:M76) -> 100 | O76: = | P76: 100
A77: C'11= | B77: =F67+F72 -> 1 | D77: D11= | E77: =B58-B77 -> 5 | I77: 2 | J77: 75 | K77: 75 | L77: 0 | M77: 0 | N77: =SUM(J77:M77) -> 150 | O77: = | P77: 150
A78: C'23= | B78: =F71+F69 -> 3 | D78: D23= | E78: =D59-B78 -> 2 | I78: 3 | J78: 0 | K78: 0 | L78: 0 | M78: 50 | N78: =SUM(J78:M78) -> 50 | O78: = | P78: 50
A79: C'24= | B79: =F71+F70 -> 5 | D79: D24= | E79: =E59-B79 -> 1 | J79: =SUM(J76:J78) -> 75 | K79: =SUM(K76:K78) -> 80 | L79: =SUM(L76:L78) -> 60 | M79: =SUM(M76:M78) -> 85
A80: C'31= | B80: =F73+F72 -> 0 | D80: D31= | E80: =B60-B80 -> 3 | J80: = | K80: = | L80: = | M80: =
A81: C'32= | B81: =F73+F68 -> 1 | D81: D32= | E81: =C60-B81 -> 9 | J81: 75 | K81: 80 | L81: 60 | M81: 85
A82: C'33= | B82: =F73+F69 -> 2 | D82: D33= | E82: =D60-B82 -> 18
M83: =SUMPRODUCT(J69:M71,J76:M78) -> 790
D84: Dij>0
A86: Шахта | B86: Населенные пункты
B87: 1 | D87: 2 | F87: 3 | H87: 4
A88: 1 | B88: 1 | C88: 6 | E88: 2 | G88: 3 | I88: 5 | J88: 100(0)
C89: 5 | D89: 5 | F89: 60 | H89: 35
A90: 2 | C90: 1 | E90: 2 | F90: 3 | G90: 5 | H90: 5 | I90: 6 | J90: 150(0)
B91: 75 | D91: 75 | G91: 2 | I91: 1
A92: 3 | B92: 0 | C92: 3 | D92: 1 | E92: 10 | F92: 2 | G92: 20 | I92: 4 | J92: 50(-1)
C93: 3 | E93: 9 | G93: 18 | H93: 50
B94: 75(1) | D94: 80(2) | F94: 60(3) | H94: 85(5)
A96: Изменение на шахте 3(добыча угля 80 тыс тонн)
A98: Шахта | B98: Населенный пункт | J98: Шахта | K98: Населенный пункт
B99: 1 | C99: 2 | D99: 3 | E99: 4 | F99: 5 | K99: 1 | L99: 2 | M99: 3 | N99: 4 | O99: 5
A100: 1 | B100: 6 | C100: 2 | D100: 3 | E100: 5 | F100: 0 | G100: 100 | J100: 1 | K100: 6 | L100: 2 | M100: 3 | N100: 5 | O100: 30 0 | P100: 100 | Q100: 70
A101: 2 | B101: 1 | C101: 2 | D101: 5 | E101: 6 | F101: 0 | G101: 150 | J101: 2 | K101: 1 | L101: 2 | M101: 5 | N101: 6 | O101: 0 | P101: 150
A102: 3 | B102: 3 | C102: 10 | D102: 20 | E102: 4 | F102: 0 | G102: 80 | J102: 3 | K102: 3 | L102: 10 | M102: 20 | N102: 4 | O102: 0 | P102: 80
B103: 75 | C103: 80 | D103: 60 | E103: 85 | F103: 30 | K103: 75 | L103: 80 | M103: 60 | N103: 85 | O103: 30
A106: Шахта | B106: Населенный пункт | J106: Шахта | K106: Населенный пункт
B107: 1 | C107: 2 | D107: 3 | E107: 4 | F107: 5 | K107: 1 | L107: 2 | M107: 3 | N107: 4 | O107: 5
A108: 1 | B108: 6 | C108: 2 | D108: 3 | E108: 5 | F108: 30 0 | G108: 100 | H108: 70 | J108: 1 | K108: 6 | L108: 70 2 | M108: 3 | N108: 5 | O108: 30 0 | P108: 100 | Q108: 70
A109: 2 | B109: 75 1 | C109: 2 | D109: 5 | E109: 6 | F109: 0 | G109: 150 | H109: 75 | J109: 2 | K109: 75 1 | L109: 2 | M109: 5 | N109: 6 | O109: 0 | P109: 150 | Q109: 75
A110: 3 | B110: 3 | C110: 10 | D110: 20 | E110: 4 | F110: 0 | G110: 80 | J110: 3 | K110: 3 | L110: 10 | M110: 20 | N110: 4 | O110: 0 | P110: 80
B111: 75 | C111: 80 | D111: 60 | E111: 85 | F111: 30 | K111: 75 | L111: 80 | M111: 60 | N111: 85 | O111: 30
L112: 10
A115: Шахта | B115: Населенный пункт | K115: Шахта | L115: Населенный пункт
B116: 1 | C116: 2 | D116: 3 | E116: 4 | F116: 5 | L116: 1 | M116: 2 | N116: 3 | O116: 4 | P116: 5
A117: 1 | B117: 6 | C117: 70 2 | D117: 3 | E117: 5 | F117: 30 0 | G117: 100 | H117: 70 | K117: 1 | L117: 6 | M117: 70 2 | N117: 3 | O117: 5 | P117: 30 0 | Q117: 100 | R117: 70
A118: 2 | B118: 75 1 | C118: 10 2 | D118: 5 | E118: 6 | F118: 0 | G118: 150 | H118: 75 | I118: 65 | K118: 2 | L118: 75 1 | M118: 10 2 | N118: 5 | O118: 6 | P118: 0 | Q118: 150 | R118: 75 | S118: 65
A119: 3 | B119: 3 | C119: 10 | D119: 20 | E119: 4 | F119: 0 | G119: 80 | K119: 3 | L119: 3 | M119: 10 | N119: 20 | O119: 80 4 | P119: 0 | Q119: 80
B120: 75 | C120: 80 | D120: 60 | E120: 85 | F120: 30 | L120: 75 | M120: 80 | N120: 60 | O120: 85 | P120: 30
C121: 10 | M121: 10 | O121: 5
A124: Шахта | B124: Населенный пункт | L124: Шахта | M124: Населенный пункт
B125: 1 | C125: 2 | D125: 3 | E125: 4 | F125: 5 | M125: 1 | N125: 2 | O125: 3 | P125: 4 | Q125: 5
A126: 1 | B126: 6 | C126: 70 2 | D126: 3 | E126: 5 | F126: 30 0 | G126: 100 | H126: 70 | L126: 1 | M126: 6 | N126: 70 2 | O126: 3 | P126: 5 | Q126: 30 0 | R126: 100
A127: 2 | B127: 75 1 | C127: 10 2 | D127: 60 5 | E127: 6 | F127: 0 | G127: 150 | H127: 75 | I127: 65 | J127: 5 | L127: 2 | M127: 75 1 | N127: 10 2 | O127: 60 5 | P127: 5 6 | Q127: 0 | R127: 150
...

Sheet 5
A1: Необходмо составить план выполнения работ так, чтобы все работы оказались выполненными, каждый рабочий был загружен только на одной работе, а суммарная стоимость выполнения всех работ была минимальной.
A6: Работы | B6: Стоимость выполнения работ, д.е.
B7: 1 рабочий | C7: 2 рабочий | D7: 3 рабочий | E7: 4 рабочий | F7: 5 рабочий
A8: 1 | B8: 3 | C8: 6 | D8: 2 | E8: 5 | F8: 11
A9: 2 | B9: 1 | C9: 2 | D9: 7 | E9: 11 | F9: 3
A10: 3 | B10: 5 | C10: 12 | D10: 11 | E10: 9 | F10: 1
A11: 4 | B11: 2 | C11: 4 | D11: 2 | E11: 10 | F11: 5
A13: Сбалансируем задачу
A15: Работы | B15: Стоимость выполнения работ, д.е.
B16: 1 рабочий | C16: 2 рабочий | D16: 3 рабочий | E16: 4 рабочий | F16: 5 рабочий
A17: 1 | B17: 3 | C17: 6 | D17: 2 | E17: 5 | F17: 11
A18: 2 | B18: 1 | C18: 2 | D18: 7 | E18: 11 | F18: 3
A19: 3 | B19: 5 | C19: 12 | D19: 11 | E19: 9 | F19: 1
A20: 4 | B20: 2 | C20: 4 | D20: 2 | E20: 10 | F20: 5
A21: 5 | B21: 0 | C21: 0 | D21: 0 | E21: 0 | F21: 0
A24: Математическая модель
A25: Чтобы все работы оказались выполненными | E25: Чтобы каждый рабочий был загружен только на одной работе
A26: Х11+Х12+Х13+Х14+Х15=1 | E26: Х11+Х21+Х31+Х41+Х51=1
A27: Х21+Х22+Х23+Х24+Х25=1 | E27: Х12+Х22+Х32+Х42+Х52=1
A28: Х31+Х32+Х33+Х34+Х35=1 | E28: Х13+Х23+Х33+Х43+Х53=1
A29: Х41+Х42+Х43+Х44+Х45=1 | E29: Х14+Х24+Х34+Х44+Х54=1
A30: Х51+Х52+Х53+Х54+Х55=1 | E30: Х15+Х25+Х35+Х45+Х55=1
A32: Целевая функция
A33: E = 3*X11 + X12 + 5*X13 + 2*X14 + 6*X21 + 2*X22 + 12*X23 + 4*X24 + 2*X31 + 7*X32 + 11*X33 + 2*X34 + 5*Х41 + 11*Х22 + 9*Х43 + 10*Х44 + 11*Х51 + 3*Х52 + 1*Х53 + 5*Х54-> min
E38: А
A39: 3 | B39: 1 | C39: 5 | D39: 2 | E39: 0 | F39: 1
A40: 6 | B40: 2 | C40: 12 | D40: 4 | E40: 0 | F40: 2
A41: 2 | B41: 7 | C41: 11 | D41: 2 | E41: 0 | F41: 2
A42: 5 | B42: 11 | C42: 9 | D42: 10 | E42: 0 | F42: 5
A43: 11 | B43: 3 | C43: 1 | D43: 5 | E43: 0 | F43: 1 | G43: dmin
A45: 3 | B45: 1 | C45: 5 | D45: 2 | E45: 1
A46: 6 | B46: 2 | C46: 12 | D46: 4 | E46: 1
A47: 2 | B47: 7 | C47: 11 | D47: 2 | E47: 1
A48: 5 | B48: 11 | C48: 9 | D48: 10 | E48: 1
A49: 11 | B49: 3 | C49: 1' | D49: 5 | E49: 1
A51: 3 | B51: 1 | C51: 5 | D51: 2 | E51: 1 | F51: 0 | G51: dmin
A52: 6 | B52: 2 | C52: 12 | D52: 4 | E52: 1 | F52: 1
A53: 2 | B53: 7 | C53: 11 | D53: 2 | E53: 1 | F53: 1
A54: 5 | B54: 11 | C54: 9 | D54: 10 | E54: 1 | F54: 4
A55: 11 | B55: 3 | C55: 1 | D55: 5 | E55: 1
A57: 3 | B57: 1' | C57: 5 | D57: 2 | E57: 1
A58: 6 | B58: 2 | C58: 12 | D58: 4 | E58: 1
A59: 2 | B59: 7 | C59: 11 | D59: 2 | E59: 1
A60: 5 | B60: 11 | C60: 9 | D60: 10 | E60: 1
A61: 11 | B61: 3 | C61: 1 | D61: 5 | E61: 1
A63: 3 | B63: 1 | C63: 5 | D63: 2 | E63: 1
A64: 6 | B64: 2 | C64: 12 | D64: 4 | E64: 1 | F64: 1 | G64: dmin
A65: 2 | B65: 7 | C65: 11 | D65: 2 | E65: 1 | F65: 1
A66: 5 | B66: 11 | C66: 9 | D66: 10 | E66: 1 | F66: 4
A67: 11 | B67: 3 | C67: 1 | D67: 5 | E67: 1
A69: 3 | B69: 1 | C69: 5 | D69: 2 | E69: 2
A70: 6 | B70: 2 | C70: 12 | D70: 4 | E70: 2
A71: 2' | B71: 7 | C71: 11 | D71: 2 | E71: 2
A72: 5 | B72: 11 | C72: 9 | D72: 10 | E72: 2
A73: 11 | B73: 3 | C73: 1 | D73: 5 | E73: 2
A75: 3 | B75: 1 | C75: 5 | D75: 2 | E75: 2
A76: 6 | B76: 2 | C76: 12 | D76: 4 | E76: 2
A77: 2 | B77: 7 | C77: 11 | D77: 2 | E77: 2
A78: 5 | B78: 11 | C78: 9 | D78: 10 | E78: 2
A79: 11 | B79: 3 | C79: 1 | D79: 5 | E79: 2
E80: A
A82: 3 | B82: 1 | C82: 5 | D82: 2 | E82: 2
A83: 6 | B83: 2 | C83: 12 | D83: 4 | E83: 2 | F83: 0 | G83: dmin
A84: 2 | B84: 7 | C84: 11 | D84: 2 | E84: 2
A85: 5 | B85: 11 | C85: 9 | D85: 10 | E85: 2 | F85: 3
A86: 11 | B86: 3 | C86: 1 | D86: 5 | E86: 2
A88: 3 | B88: 1 | C88: 5 | D88: 2 | E88: 2
A89: 6 | B89: 2' | C89: 12 | D89: 4 | E89: 2
A90: 2 | B90: 7 | C90: 11 | D90: 2 | E90: 2
A91: 5 | B91: 11 | C91: 9 | D91: 10 | E91: 2
A92: 11 | B92: 3 | C92: 1 | D92: 5 | E92: 2
B93: A | E93: A
A95: 3 | B95: 1 | C95: 5 | D95: 2 | E95: 2 | F95: 1 | G95: dmin
A96: 6 | B96: 2 | C96: 12 | D96: 4 | E96: 2 | F96: 2
A97: 2 | B97: 7 | C97: 11 | D97: 2 | E97: 2
A98: 5 | B98: 11 | C98: 9 | D98: 10 | E98: 2 | F98: 3
A99: 11 | B99: 3 | C99: 1 | D99: 5 | E99: 2
A101: 3 | B101: 2 | C101: 5 | D101: 2' | E101: 3
A102: 6 | B102: 3 | C102: 12 | D102: 4 | E102: 3
A103: 2 | B103: 8 | C103: 11 | D103: 2 | E103: 3
A104: 5 | B104: 12 | C104: 9 | D104: 10 | E104: 3
A105: 11 | B105: 4 | C105: 1 | D105: 5 | E105: 3
A107: 3 | B107: 2 | C107: 5 | D107: 2 | E107: 3
A108: 6 | B108: 3 | C108: 12 | D108: 4 | E108: 3
A109: 2 | B109: 8 | C109: 11 | D109: 2 | E109: 3
A110: 5 | B110: 12 | C110: 9 | D110: 10 | E110: 3
A111: 11 | B111: 4 | C111: 1 | D111: 5 | E111: 3
A113: Оптимальное решение: 1 рабочему следует работать на 4 работе, 2 рабочему на 2, 3 рабочему на 1, 5 рабочему на 3 работе, а 4 рабочий задействован не будет.
A116: Общая стоимость всех работ составят Е=2+3+1+2=8 д.е.

Sheet 6
B24: Р1 | C24: Р2
A25: Мин объем выпуска (тонн) | B25: 100 | C25: 120
A26: Прибыль от 1 тонны (тыс.ден.ед.) | B26: 2 | C26: 4
A27: Общая прибыль (млн ден. ед) | B27: 1.5
A30: Мат модель
A31: X1>=100
A32: X2>=120
A33: 2X1+4X2>=1500
A34: E=10X1+6X2+0,1X1^2+0,1X2^2->min
B37: (10+0,2*X1, 6+0,2*X2)
A41: Начальное допустимое решение
A42: 10X1+6X2->min
A43: X1>=100
A44: X2>=120 | C44: E(0)= | D44: =10*100+325*6+0.1*100*100+0.1*325*325 -> 14512.5
A45: 2X1+4X2>=1500 | C45: Точность(e) = | D45: 0.5
A47: Итерация 1
A49: Градиент Е в точке ОДР
A50: grad E(X(0))=(10+0,2*100, 6+0,2*325)=(30, 71)
A52: Угловая точка ОДР
A53: 30X1+71X2->min
A54: X1>=100
A55: X2>=120 | B55: Вывод: | C55: Поиск нового решения от т. X(0)=(100;325) к X*=(510;120)
A56: 2X1+4X2>=1500
A58: Уравнения для перехода к новому решению
A59: X1(1)=X1(0)+l(X1*-X1(0))= | B59: 100+l(510-100)
A60: X2(1)=X2(0)+l(X2*-X2(0))= | B60: 325+l(120-325)
A63: Коэффициент лямбда
A64: E=10*(100+410l)+6*(325-205l)+0,1*(100+410l)*(100+410l)+0,1*(325-205l)*(325-205l) | G64: =14512,5-2255l+21012,5l^2
A65: dE/dl=-2255+42025l=0
A66: l=0,054
A68: X1(1)=X1(0)+l(X1*-X1(0))= | B68: 100+l(510-100)= 122,14
A69: X2(1)=X2(0)+l(X2*-X2(0))= | B69: 325+l(120-325)= 313,93
A70: Целевая функция Е(1) | B70: =10*122.14+6*313.93+0.1*122.14^2+0.1*313.93^2 -> 14452.002
A72: Условие окончания
A73: deltaE=|E(1)-E(0)|=|14452,00245-14512,5| | C73: 60.49755 | E73: deltaE>e
A75: Итерация 2
A77: Градиент Е в точке ОДР
A78: grad E(X(0))=(10+0,2*122,14, 6+0,2*313,93)=(34,428, 68,786)
A80: Угловая точка ОДР
A81: 34.428X1+68.786X2->min
A82: X1>=100
A83: X2>=120
A84: 2X1+4X2>=1500 | B84: Вывод: | C84: Поиск нового решения от т. X(1)=(122,14;313,93) к X(1)*=(100;325)
A86: Уравнения для перехода к новому решению
A87: X1(2)=X1(1)+l(X1(1)*-X1(1))= | B87: 122,14+l(100-122,14)
A88: X2(2)=X2(1)+l(X2(1)*-X2(1))= | B88: 313,93+l(325-313,93)
A90: Коэффициент лямбда
A91: E=10*(122,14-22,14l)+6*(313,93+11,07l)+0,1*(122,14-22,14l)*(122,14-22,14l)+0,1*(313,93+11,07l)*(313,93+11,07l) = | J91: 14452,0045-0,7749l+61,27l^2
A92: dE/dl=-0,7749+122,54l=0
A93: l=0,0063
A95: Уравнения для перехода к новому решению | I95: X1 | J95: X2
A96: X1(2)=X1(1)+l(X1(1)*-X1(1))= | B96: 122,14+l(100-122,14)=122 | I96: 122 | J96: 314
A97: X2(2)=X2(1)+l(X2(1)*-X2(1))= | B97: 313,93+l(325-313,93)=314 | H97: Целевая функция | I97: =10*I96+6*J96+0.1*I96^2+0.1*J96^2 -> 14452 | J97: -> | K97: min
A98: Целевая функция Е(2) | B98: =10*122+6*314+0.1*122^2+0.1*314^2 -> 14452 | H98: Ограничения | I98: =2*I96+4*J96 -> 1500 | J98: >= | K98: 1500
I99: =I96 -> 122 | J99: >= | K99: 100
A100: Условие окончания | I100: =J96 -> 314 | J100: >= | K100: 120
A101: deltaE=|E(2)-E(1)|=|14452-14452,00245| | C101: 0.00245 | E101: deltaE<e

Sheet 7
A1: Выделенные средства, млн ден.ед. | C1: Предприятие
C2: П1 | D2: П2 | E2: П3 | F2: П4
A3: 0 | C3: 0 | D3: 0 | E3: 0 | F3: 0
A4: 10 | C4: 20 | D4: 15 | E4: 25 | F4: 12
A5: 20 | C5: 22 | D5: 18 | E5: 30 | F5: 22
A6: 30 | C6: 28 | D6: 30 | E6: 32 | F6: 30
A7: 40 | C7: 40 | D7: 50 | E7: 40 | F7: 38
A8: 50 | C8: 52 | D8: 55 | E8: 46 | F8: 45
A9: 60 | C9: 60 | D9: 70 | E9: 53 | F9: 50
A11: S0=60
A12: E=Z1+Z2+Z3+Z4
A14: Шаг 4 (выделение средств предприятию П4)
A16: S3 | B16: U*4 | C16: E*4
A17: 0 | B17: 0 | C17: 0
A18: 10 | B18: 10 | C18: 12
A19: 20 | B19: 20 | C19: 22
A20: 30 | B20: 30 | C20: 30
A21: 40 | B21: 40 | C21: 38
A22: 50 | B22: 50 | C22: 45
A23: 60 | B23: 60 | C23: 50
A25: Шаг 3 (выделение средств предприятиям П3 и П4)
A27: S2 | B27: U3 | C27: Z3 | D27: S3 | E27: E*4 | F27: E3 | G27: U*3 | H27: E*3
A28: 0 | B28: 0 | C28: 0 | D28: 0 | E28: 0 | F28: 0 | G28: 0 | H28: 0
A29: 10 | B29: 0 | C29: 0 | D29: 10 | E29: 12 | F29: =0+12 -> 12 | G29: 10 | H29: 25
B30: 10 | C30: 25 | D30: 0 | E30: 0 | F30: 25
A31: 20 | B31: 0 | C31: 0 | D31: 20 | E31: 22 | F31: 22 | G31: 10 | H31: 37
B32: 10 | C32: 25 | D32: 10 | E32: 12 | F32: =C32+E32 -> 37
B33: 20 | C33: 30 | D33: 0 | E33: 0 | F33: 30
A34: 30 | B34: 0 | C34: 0 | D34: 30 | E34: 30 | F34: 30 | G34: 10 | H34: 47
B35: 10 | C35: 25 | D35: 20 | E35: 22 | F35: =E35+C35 -> 47
B36: 20 | C36: 30 | D36: 10 | E36: 12 | F36: =E36+C36 -> 42
B37: 30 | C37: 32 | D37: 0 | E37: 0 | F37: 32
A38: 40 | B38: 0 | C38: 0 | D38: 40 | E38: 38 | F38: =E38+C38 -> 38 | G38: 10 | H38: 55
B39: 10 | C39: 25 | D39: 30 | E39: 30 | F39: =E39+C39 -> 55
B40: 20 | C40: 30 | D40: 20 | E40: 22 | F40: =E40+C40 -> 52
B41: 30 | C41: 32 | D41: 10 | E41: 12 | F41: =E41+C41 -> 44
B42: 40 | C42: 40 | D42: 0 | E42: 0 | F42: =E42+C42 -> 40
A43: 50 | B43: 0 | C43: 0 | D43: 50 | E43: 45 | F43: =E43+C43 -> 45 | G43: 10 | H43: 63
B44: 10 | C44: 25 | D44: 40 | E44: 38 | F44: =E44+C44 -> 63
B45: 20 | C45: 30 | D45: 30 | E45: 30 | F45: =E45+C45 -> 60
B46: 30 | C46: 32 | D46: 20 | E46: 22 | F46: =E46+C46 -> 54
B47: 40 | C47: 40 | D47: 10 | E47: 12 | F47: =E47+C47 -> 52
B48: 50 | C48: 46 | D48: 0 | E48: 0 | F48: =E48+C48 -> 46
A49: 60 | B49: 0 | C49: 0 | D49: 60 | E49: 50 | F49: =E49+C49 -> 50 | G49: 10 | H49: 70
B50: 10 | C50: 25 | D50: 50 | E50: 45 | F50: =E50+C50 -> 70
B51: 20 | C51: 30 | D51: 40 | E51: 38 | F51: =E51+C51 -> 68
B52: 30 | C52: 32 | D52: 30 | E52: 30 | F52: =E52+C52 -> 62
B53: 40 | C53: 40 | D53: 20 | E53: 22 | F53: =E53+C53 -> 62
B54: 50 | C54: 46 | D54: 10 | E54: 12 | F54: =E54+C54 -> 58
B55: 60 | C55: 53 | D55: 0 | E55: 0 | F55: =E55+C55 -> 53
A57: Шаг 2 (выделение средств предприятиям П2, П3, П4)
A59: S1 | B59: U2 | C59: Z2 | D59: S2 | E59: E*3 | F59: E2 | G59: U*2 | H59: E*2
A60: 0 | B60: 0 | C60: 0 | D60: 0 | E60: 0 | F60: 0 | G60: 0 | H60: 0
A61: 10 | B61: 0 | C61: 0 | D61: 10 | E61: 25 | F61: =C61+E61 -> 25 | G61: 0 | H61: 25
B62: 10 | C62: 15 | D62: 0 | E62: 0 | F62: =C62+E62 -> 15
A63: 20 | B63: 0 | C63: 0 | D63: 20 | E63: 37 | F63: =C63+E63 -> 37 | G63: 10 | H63: 40
B64: 10 | C64: 15 | D64: 10 | E64: 25 | F64: =C64+E64 -> 40
B65: 20 | C65: 18 | D65: 0 | E65: 0 | F65: =C65+E65 -> 18
A66: 30 | B66: 0 | C66: 0 | D66: 30 | E66: 47 | F66: =C66+E66 -> 47 | G66: 10 | H66: 52
B67: 10 | C67: 15 | D67: 20 | E67: 37 | F67: =C67+E67 -> 52
B68: 20 | C68: 18 | D68: 10 | E68: 25 | F68: =C68+E68 -> 43
B69: 30 | C69: 30 | D69: 0 | E69: 0 | F69: =C69+E69 -> 30
A70: 40 | B70: 0 | C70: 0 | D70: 40 | E70: 55 | F70: =C70+E70 -> 55 | G70: 10 | H70: 62
B71: 10 | C71: 15 | D71: 30 | E71: 47 | F71: =C71+E71 -> 62
B72: 20 | C72: 18 | D72: 20 | E72: 37 | F72: =C72+E72 -> 55
B73: 30 | C73: 30 | D73: 10 | E73: 25 | F73: =C73+E73 -> 55
B74: 40 | C74: 50 | D74: 0 | E74: 0 | F74: =C74+E74 -> 50
A75: 50 | B75: 0 | C75: 0 | D75: 50 | E75: 63 | F75: =C75+E75 -> 63 | G75: 40 | H75: 75
B76: 10 | C76: 15 | D76: 40 | E76: 55 | F76: =C76+E76 -> 70
B77: 20 | C77: 18 | D77: 30 | E77: 47 | F77: =C77+E77 -> 65
B78: 30 | C78: 30 | D78: 20 | E78: 37 | F78: =C78+E78 -> 67
B79: 40 | C79: 50 | D79: 10 | E79: 25 | F79: =C79+E79 -> 75
B80: 50 | C80: 55 | D80: 0 | E80: 0 | F80: =C80+E80 -> 55
A81: 60 | B81: 0 | C81: 0 | D81: 60 | E81: 70 | F81: =C81+E81 -> 70 | G81: 40 | H81: 87
B82: 10 | C82: 15 | D82: 50 | E82: 63 | F82: =C82+E82 -> 78
B83: 20 | C83: 18 | D83: 40 | E83: 55 | F83: =C83+E83 -> 73
B84: 30 | C84: 30 | D84: 30 | E84: 47 | F84: =C84+E84 -> 77
B85: 40 | C85: 50 | D85: 20 | E85: 37 | F85: =C85+E85 -> 87
B86: 50 | C86: 55 | D86: 10 | E86: 25 | F86: =C86+E86 -> 80
B87: 60 | C87: 70 | D87: 0 | E87: 0 | F87: =C87+E87 -> 70
A89: Шаг 1 ( выделение средств предприятиям П1, П2, П3, П4)
A91: S0 | B91: U1 | C91: Z1 | D91: S1 | E91: E*2 | F91: E1 | G91: U*1 | H91: E*1
A92: 60 | B92: 0 | C92: 0 | D92: 60 | E92: 87 | F92: =E92+C92 -> 87 | G92: 10 | H92: =MAX(F92:F98) -> 95
B93: 10 | C93: 20 | D93: 50 | E93: 75 | F93: =E93+C93 -> 95
B94: 20 | C94: 22 | D94: 40 | E94: 62 | F94: =E94+C94 -> 84
B95: 30 | C95: 28 | D95: 30 | E95: 52 | F95: =E95+C95 -> 80
B96: 40 | C96: 40 | D96: 20 | E96: 40 | F96: =E96+C96 -> 80
B97: 50 | C97: 52 | D97: 10 | E97: 25 | F97: =E97+C97 -> 77
B98: 60 | C98: 60 | D98: 0 | E98: 0 | F98: =E98+C98 -> 60
A100: Цикл безусловной оптимизации
A102: Для первого шага (выделение средств предприятию П1) получено безусловно оттимальное решение: U*1= 10 млн ден.ел. Для предириятий П2, ПЗ и П4 остается 50 млн ден.ед. Таким образом, состояние в начале второго шага S1=50. Для этого состояния определяется оптимальное решение: U*2 = 40 (предприятию П2 выделяется 40 млн ден.ед.). Для предприятий П3 и П4 остается 20 млн ден.ед. (состояние в начале третьего шага S2=20). Для этого состояния определяется оптимальное решение: U*3 = 10 (пред-приятию П3 выделяется 10 млн ден.ед.). Для предприятия П4 остается 0 млн ден.ед. (S3=0). Поэтому U*4=0.
A109: U*1=10 | C109: E = 20+50+25=95 млн. ден. ед.
A110: U*2=40
A111: U*3=10
A112: U*4=0
A114: Таким образом, оптимальное решение задачи следующее. Предприятию П1 следует выделить 10 млн ден.ед., предприятию П2 - 40 млн ден.ед., предприятию П3 - выделить 10 млн ден.ед., предприятию П4 - не выделять средства. Общая прибыль составит 95 млн ден.ед., в том числе прибыль предприятия П1 - 20 млн ден.ед., П2 - 50 млн ден.ед., П3 - 25 млн ден.ед., П4 - 0 млн ден.ед.

Sheet 8_1
A1: На участке выпускаются детали двух видов. Заготовки для выпуска деталей поступают на участок через каждые 6±2 минуты. Все заготовки обрабатываются на станке A; время обработки детали на станке распределено по экспоненциальному закону и составляет в среднем 5 минут.
A5: 10% деталей, выпущенных на станке A, продаются как готовые изделия (детали типа1). Остальные проходят дальнейшую обработку (из них выпускаются детали типа 2). Детали типа 1 со станка A поступают на два одинаковых станка (B1 и B2); время обработки одной детали на этих станках распределено по экспоненциальному закону и составляет в среднем 12 минут. Перед станками B1 и B2 установлен общий накопитель, вмещающий пять деталей; при его заполнении все поступающие детали типа 1 направляются на станок C, на котором обработка занимает ровно 7 минут.
A13: Затраты (в денежных единицах), связанные с работой и простоями каждого станка (в минуту), приведены в таблице.
B15: A | C15: B | D15: C
A16: Работа | B16: 0.3 | C16: 0.6 | D16: 0.5
A17: Простой | B17: 0.1 | C17: 0.2 | D17: 0.1
A18: Прочие расходы, связанные с выпуском деталей типа 1 и 2, составляют 2 и 8 д.е. соответственно. Детали типа 1 продаются по цене 5 д.е., типа 2 - 22 д.е.
A20: 1. Найти характеристики работы станка A (8.4, 8.7). 2. Найти характеристики работы группы станков B1-B2 (8.13, 8.4, 8.9). Поток деталей на эту группу станков считать пуассоновским. 3. Рассчитать характеристики работы станка C (8.13, 8.4, 8.7). Поток деталей на станок C считать пуассоновскими. 4. Найти прибыль от работы участка за 8 часов (8.6, 8.7, 8.9). 5. Найти вероятность того, что деталь, поступившая на станки B1-B2, сразу же начнет обрабатываться (не будет ждать в очереди) (8.5, 8.9, пример из 8.8).
A28: 6. Найти характеристики работы всех станков и прибыль от работы участка (за 8 часов) при следующих изменениях: заготовки поступают на обработку чаще (через каждые 4±2 минуты), а станок A заменен на новый (A1); среднее время обработки одной детали на станке A1 - 3 минуты (экспоненциальная случайная величина). Для нового станка A1 затраты на одну минуту работы и простоя - 0,4 и 0,2 д.е. соответственно. Определить, яляется ли предлагаемые изменения целесообразными.

Sheet 8_2
A1: Найти характеристики работы станка A | B1: G/M/1
A3: На участке выпускаются детали двух видов. Заготовки для выпуска деталей поступают на участок через каждые 6±2 минуты. Все заготовки обрабатываются на станке A; время обработки детали на станке распределено по экспоненциальному закону и составляет в среднем 5 минут.
B7: A
A8: Работа | B8: 0.3
A9: Простой | B9: 0.1
A10: Прочие расходы, связанные с выпуском деталей типа 1 и 2, составляют 2 и 8 д.е. соответственно. Детали типа 1 продаются по цене 5 д.е., типа 2 - 22 д.е.
A13: Параметры станка А
A14: Интенсивность потока заявок, дет/мин. | B14: 𝜆 = 1/6 = | C14: =1/6 -> 0.16666667 | D14: (4+8)/2=6
A15: Количество каналов | B15: m = | C15: 1
A16: Среднее время обслуживания заявки | B16: x̅ = | C16: 5
A17: Интенвивность обсл. заявок, дет/мин. | B17: µ = 1/x̅ = | C17: =1/C16 -> 0.2
A19: Характеристики станка А
A20: Вероятность простоя, Ро | B20: 1 - ρ= | C20: =1-C30 -> 0.16666667
A21: Вероятность отказа, Ротк | C21: 0
A22: Вероятность обслуживания, Робсл | C22: 1
A23: Коэф.загрузки, U | B23: ρ = | C23: =C30 -> 0.83333333
A24: Средняя длина очереди, q̅ | B24: (ρ^2*(v^2+ε^2))/ (2*(1-ρ)) = | C24: =(C30^2*(C31^2+C32^2))/(2*(1-C30)) -> 2.3148148
A25: Среднее число занятый каналов, S̅ | B25: m*U= | C25: =C15*C23 -> 0.83333333
A26: На обслуживании в очереди, k̅ | B26: q̅ + S̅ = | C26: =C24+C25 -> 3.1481481
A27: Среднее время ожидания обслучивания, w̅ | B27: q̅ / γ = | C27: =C24/C29 -> 13.888889
A28: В очереди и на обслуживании, t̅ | B28: w̅ + x̅ = | C28: =C27+C16 -> 18.888889
A29: Пропускная способность, γ | B29: 𝜆 = | C29: =C14 -> 0.16666667
A30: Нагрузка на канал, ρ | B30: 𝜆 / (m*µ)= | C30: =C14/(C15*C17) -> 0.83333333
A31: Коэфф вариации интервалов времени между заявками, v | B31: σ/x̅ = | C31: =2/6 -> 0.33333333
A32: Коэфф вариации времени обслуживания, ε | C32: 1

Sheet 8_3
A1: Перед станками B1 и B2 установлен общий накопитель, вмещающий пять деталей; при его заполнении все поступающие детали типа 1 направляются на станок C, на котором обработка занимает ровно 7 минут.
A4: M/D/1
A6: Параметры станков C
A7: Интенсивность потока заявок, дет/мин | B7: P𝜆 = | C7: ='8_4'!C10*'8_4'!C17 -> 0.013809433
A8: Количество каналов | B8: m = | C8: 1
A9: Среднее время обслуживания заявки | B9: x̅ = | C9: 7
A10: Интенвивность обсл. заявок, дет/мин | B10: µ = 1/x̅ = | C10: =1/C9 -> 0.14285714
A12: Характеристики станков C
A13: Вероятность простоя, Ро | B13: 1 - ρ = | C13: =1-C23 -> 0.90333397
A14: Вероятность отказа, Ротк | C14: 0
A15: Вероятность обслуживания, Робсл | B15: 1-Ротк= | C15: =1-C14 -> 1
A16: Коэф.загрузки, U | B16: ρ = | C16: =C23*C15 -> 0.096666034
A17: Средняя длина очереди, q̅ | B17: (ρ^2*(v^2+ε^2))/ (2*(1-ρ))= | C17: =(C23^2*(C24^2+C25^2))/(2*(1-C23)) -> 0.0051721304
A18: Среднее число занятый каналов, S̅ | B18: m*U= | C18: =C8*C16 -> 0.096666034
A19: На обслуживании в очереди, k̅ | B19: q̅ + S̅ = | C19: =C17+C18 -> 0.10183816
A20: Среднее время ожидания обслучивания, w̅ | B20: q̅ / γ = | C20: =C17/C22 -> 0.37453603
A21: В очереди и на обслуживании, t̅ | B21: w̅ + x̅ = | C21: =C20+C9 -> 7.374536
A22: Пропускная способность, γ | B22: 𝜆 = | C22: =C7 -> 0.013809433
A23: Нагрузка на канал, ρ | B23: 𝜆 / (m*µ)= | C23: =C7/(C8*C10) -> 0.096666034 | D23: <1
A24: Коэфф вариации интервалов времени между заявками, v | C24: 1
A25: Коэфф вариации времени обслуживания, ε | C25: 0

Sheet 8_4
A1: Найти характеристики работы группы станков B1-B2 (8.13, 8.4, 8.9). Поток деталей на эту группу станков считать пуассоновским.
A4: Детали типа 1 со станка A поступают на два одинаковых станка (B1 и B2);
A5: Время обработки одной детали на этих станках распределено по экспоненциальному закону и составляет в среднем 12 минут. Перед станками B1 и B2 установлен общий накопитель, вмещающий пять деталей;
A8: М/M/2
A9: Параметры станков В1-В2
A10: Интенсивность потока заявок, дет/мин | B10: 𝜆 = 0,9*(1/6 )= | C10: =(1/6)*0.9 -> 0.15
A11: Количество каналов | B11: m = | C11: 2
A12: Среднее время обслуживания заявки | B12: x̅ = | C12: 12
A13: Интенвивность обсл. заявок, дет/мин | B13: µ = 1/x̅ = | C13: =1/C12 -> 0.083333333
A15: Характеристики станков В1-В2
A16: Вероятность простоя, Ро | C16: =((221/50)+(29853279/5000000))^(-1) -> 0.096240316
A17: Вероятность отказа, Ротк | B17: (mρ)^(m+n)/(m^n⋅m!) *P0 = | C17: =((C11*C26)^7/(2^5*2))*C16 -> 0.09206289
A18: Вероятность обслуживания, Робсл | B18: 1-Ротк= | C18: =1-C17 -> 0.90793711
A19: Коэф.загрузки, U | B19: ρ * (1-Ротк) = | C19: =C26*C18 -> 0.8171434
A20: Средняя длина очереди, q̅ | B20: ((mρ)^(m+1)∗P_0)/(m⋅m!)∗(1-(n+1) ρ^n+nρ^(n+1))/(1-ρ)^2 = | C20: =(((C26*2)^(2+1)*C16)/(2*2))*((1-6*C26^5+5*C26^6)/((1-C26)^2)) -> 1.603348
A21: Среднее число занятый каналов, S̅ | B21: m*U= | C21: =C11*C19 -> 1.6342868
A22: На обслуживании в очереди, k̅ | B22: q̅ + S̅ = | C22: =C20+C21 -> 3.2376348
A23: Среднее время ожидания обслучивания, w̅ | B23: q̅ / γ = | C23: =C20/C25 -> 11.772827
A24: В очереди и на обслуживании, t̅ | B24: w̅ + x̅ = | C24: =C23+C12 -> 23.772827
A25: Пропускная способность, γ | B25: µ * S̅ = | C25: =C13*C21 -> 0.13619057
A26: Нагрузка на канал, ρ | B26: 𝜆 / (m*µ)= | C26: =C10/(C11*C13) -> 0.9 | D26: <1
A27: 5.Вероятность отсутствия очереди, Р(j≤1) | B27: P0+P(1)=P0+(mρ)^(m−1)/((m−1)!) P0 = | C27: =C16+(C11*C26)*C16 -> 0.26947289

Sheet 8_5
A1: Найти характеристики работы станка A1 | B1: G/M/1
A3: заготовки поступают на обработку чаще (через каждые 4±2 минуты), а станок A заменен на новый (A1); среднее время обработки одной детали на станке A1 - 3 минуты (экспоненциальная случайная величина).
B7: A1
A8: Работа | B8: 0.4
A9: Простой | B9: 0.2
A13: Параметры станка А
A14: Интенсивность потока заявок, дет/мин. | B14: 𝜆 = 1/4 = | C14: =1/4 -> 0.25 | D14: (2+6)/2=4
A15: Количество каналов | B15: m = | C15: 1
A16: Среднее время обслуживания заявки | B16: x̅ = | C16: 3
A17: Интенвивность обсл. заявок, дет/мин. | B17: µ = 1/x̅ = | C17: =1/C16 -> 0.33333333
A19: Характеристики станка А
A20: Вероятность простоя, Ро | B20: 1 - ρ= | C20: =1-C30 -> 0.25
A21: Вероятность отказа, Ротк | C21: 0
A22: Вероятность обслуживания, Робсл | C22: 1
A23: Коэф.загрузки, U | B23: ρ = | C23: =C30 -> 0.75
A24: Средняя длина очереди, q̅ | B24: (ρ^2*(v^2+ε^2))/ (2*(1-ρ)) = | C24: =(C30^2*(C31^2+C32^2))/(2*(1-C30)) -> 1.40625
A25: Среднее число занятый каналов, S̅ | B25: m*U= | C25: =C15*C23 -> 0.75
A26: На обслуживании в очереди, k̅ | B26: q̅ + S̅ = | C26: =C24+C25 -> 2.15625
A27: Среднее время ожидания обслучивания, w̅ | B27: q̅ / γ = | C27: =C24/C29 -> 5.625
A28: В очереди и на обслуживании, t̅ | B28: w̅ + x̅ = | C28: =C27+C16 -> 8.625
A29: Пропускная способность, γ | B29: 𝜆 = | C29: =C14 -> 0.25
A30: Нагрузка на канал, ρ | B30: 𝜆 / (m*µ)= | C30: =C14/(C15*C17) -> 0.75
A31: Коэфф вариации интервалов времени между заявками, v | B31: σ/x̅ = | C31: =2/4 -> 0.5
A32: Коэфф вариации времени обслуживания, ε | C32: 1

Sheet 8_6
A1: Найти характеристики работы группы станков B1-B2 (8.13, 8.4, 8.9). Поток деталей на эту группу станков считать пуассоновским.
A4: Детали типа 1 со станка A поступают на два одинаковых станка (B1 и B2);
A5: Время обработки одной детали на этих станках распределено по экспоненциальному закону и составляет в среднем 12 минут. Перед станками B1 и B2 установлен общий накопитель, вмещающий пять деталей;
A9: Параметры станков В1-В2
A10: Интенсивность потока заявок, дет/мин | B10: 𝜆 = 0,9*(1/4 )= | C10: =(1/4)*0.9 -> 0.225
A11: Количество каналов | B11: m = | C11: 2
A12: Среднее время обслуживания заявки | B12: x̅ = | C12: 12
A13: Интенвивность обсл. заявок, дет/мин | B13: µ = 1/x̅ = | C13: =1/C12 -> 0.083333333
A15: Характеристики станков В1-В2
A16: Вероятность простоя, Ро | C16: =((1469/200)+(27^8-19683*20^5)/(28000*20^4))^(-1) -> 0.017753153
A17: Вероятность отказа, Ротк | B17: (mρ)^(m+n)/(m^n⋅m!) *P0 = | C17: =((C11*C26)^7/(2^5*2))*C16 -> 0.2901629
A18: Вероятность обслуживания, Робсл | B18: 1-Ротк= | C18: =1-C17 -> 0.7098371
A19: Коэф.загрузки, U | B19: ρ * (1-Ротк) = | C19: =C26*C18 -> 0.95828009 | D19: >0,85
A20: Средняя длина очереди, q̅ | B20: ((mρ)^(m+1)∗P_0)/(m⋅m!)∗(1-(n+1) ρ^n+nρ^(n+1))/(1-ρ)^2 = | C20: =(((C26*2)^(2+1)*C16)/(2*2))*((1-6*C26^5+5*C26^6)/((1-C26)^2)) -> 3.1114185
A21: Среднее число занятый каналов, S̅ | B21: m*U= | C21: =C11*C19 -> 1.9165602
A22: На обслуживании в очереди, k̅ | B22: q̅ + S̅ = | C22: =C20+C21 -> 5.0279786
A23: Среднее время ожидания обслучивания, w̅ | B23: q̅ / γ = | C23: =C20/C25 -> 19.481268
A24: В очереди и на обслуживании, t̅ | B24: w̅ + x̅ = | C24: =C23+C12 -> 31.481268
A25: Пропускная способность, γ | B25: µ * S̅ = | C25: =C13*C21 -> 0.15971335
A26: Нагрузка на канал, ρ | B26: 𝜆 / (m*µ)= | C26: =C10/(C11*C13) -> 1.35 | D26: >1
A27: 5.Вероятность отсутствия очереди, Р(j≤1) | B27: P0+P(1)=P0+(mρ)^(m−1)/((m−1)!) P0 = | C27: =C16+(C11*C26)*C16 -> 0.065686667

Sheet 8_7
A1: Перед станками B1 и B2 установлен общий накопитель, вмещающий пять деталей; при его заполнении все поступающие детали типа 1 направляются на станок C, на котором обработка занимает ровно 7 минут.
A6: Параметры станков C
A7: Интенсивность потока заявок, дет/мин | B7: P𝜆 = | C7: ='8_6'!C10*'8_6'!C17 -> 0.065286652
A8: Количество каналов | B8: m = | C8: 1
A9: Среднее время обслуживания заявки | B9: x̅ = | C9: 7
A10: Интенвивность обсл. заявок, дет/мин | B10: µ = 1/x̅ = | C10: =1/C9 -> 0.14285714
A12: Характеристики станков C
A13: Вероятность простоя, Ро | B13: 1 - ρ = | C13: =1-C23 -> 0.54299344
A14: Вероятность отказа, Ротк | C14: 0
A15: Вероятность обслуживания, Робсл | B15: 1-Ротк= | C15: =1-C14 -> 1
A16: Коэф.загрузки, U | B16: ρ = | C16: =C23*C15 -> 0.45700656 | D16: <0,75
A17: Средняя длина очереди, q̅ | B17: (ρ^2*(v^2+ε^2))/ (2*(1-ρ))= | C17: =(C23^2*(C24^2+C25^2))/(2*(1-C23)) -> 0.19231816
A18: Среднее число занятый каналов, S̅ | B18: m*U= | C18: =C8*C16 -> 0.45700656
A19: На обслуживании в очереди, k̅ | B19: q̅ + S̅ = | C19: =C17+C18 -> 0.64932472
A20: Среднее время ожидания обслучивания, w̅ | B20: q̅ / γ = | C20: =C17/C22 -> 2.9457501
A21: В очереди и на обслуживании, t̅ | B21: w̅ + x̅ = | C21: =C20+C9 -> 9.9457501
A22: Пропускная способность, γ | B22: 𝜆 = | C22: =C7 -> 0.065286652
A23: Нагрузка на канал, ρ | B23: 𝜆 / (m*µ)= | C23: =C7/(C8*C10) -> 0.45700656 | D23: <1
A24: Коэфф вариации интервалов времени между заявками, v | C24: 1
A25: Коэфф вариации времени обслуживания, ε | C25: 0

Sheet 8_8
A1: Найти прибыль от работы участка за 8 часов (8.6, 8.7, 8.9)
A3: Выручка от обслуживания заявок в течении времени Т:
A4: V = γ*C*T=V(A)+V(B1-B2)+V(C)= | E4: =B15*B16*480+C15*C16*480+D15*D16*480 -> 2976
A5: Затраты связанные собслуживанием заявок в канале в в течение времени Т:
A6: Zобсл = γ* Cобсл* T= | E6: =B15*B17*480+C15*C17*480+D15*D17*480 -> 1104
A7: Затраты, связанные с эксплуатацией канала в течение времени T:
A8: Zэксп = ( S̅ * Cраб + (m - S̅ ) *Cпр )*T= | E8: =(B19*B11+(B20-B19)*B12)*B18+(C19*C11+(C20-C19)*C12)*B18+(D19*D11+(D20-D19)*D12)*B18 -> 863.72481
B10: A | C10: B | D10: C
A11: Работа | B11: 0.4 | C11: 0.6 | D11: 0.5
A12: Простой | B12: 0.2 | C12: 0.2 | D12: 0.1
A13: Прочие расходы, связанные с выпуском деталей типа 1 и 2, составляют 2 и 8 д.е. соответственно. Детали типа 1 продаются по цене 5 д.е., типа 2 - 22 д.е.
A15: γ | B15: ='8_5'!C29 -> 0.25 | C15: ='8_6'!C25 -> 0.15971335 | D15: ='8_7'!C22 -> 0.065286652
A16: Выручка | B16: 5 | C16: 22 | D16: 22
A17: Прочие | B17: 2 | C17: 8 | D17: 8
A18: Т, мин | B18: 480
A19: S̅ | B19: ='8_5'!C25 -> 0.75 | C19: ='8_6'!C21 -> 1.9165602 | D19: ='8_7'!C18 -> 0.45700656
A20: m | B20: 1 | C20: 2 | D20: 1
A22: Общая прибль: | C22: V - Zобсл - Zэксп = | E22: =E4-E6-E8 -> 1008.2752

Sheet 8_9
A1: Характеристики | C1: А | D1: В1-В2 | E1: С | F1: А1 | G1: В1"-В2" | H1: С"
A2: P0 | C2: ='8_2'!C20 -> 0.16666667 | D2: ='8_4'!C16 -> 0.096240316 | E2: ='8_3'!C13 -> 0.90333397 | F2: ='8_5'!C20 -> 0.25 | G2: ='8_6'!C16 -> 0.017753153 | H2: ='8_7'!C13 -> 0.54299344
A3: Pотк | C3: 0 | D3: ='8_4'!C17 -> 0.09206289 | E3: ='8_3'!C14 -> 0 | F3: ='8_5'!C21 -> 0 | G3: ='8_6'!C17 -> 0.2901629 | H3: ='8_7'!C14 -> 0
A4: Pобсл | C4: ='8_2'!C22 -> 1 | D4: ='8_4'!C18 -> 0.90793711 | E4: ='8_3'!C15 -> 1 | F4: ='8_5'!C22 -> 1 | G4: ='8_6'!C18 -> 0.7098371 | H4: ='8_7'!C15 -> 1
A5: ρ | C5: ='8_2'!C30 -> 0.83333333 | D5: ='8_4'!C26 -> 0.9 | E5: ='8_3'!C23 -> 0.096666034 | F5: ='8_5'!C30 -> 0.75 | G5: ='8_6'!C26 -> 1.35 | H5: ='8_7'!C23 -> 0.45700656
A6: U | C6: ='8_2'!C23 -> 0.83333333 | D6: ='8_4'!C19 -> 0.8171434 | E6: ='8_3'!C16 -> 0.096666034 | F6: ='8_5'!C23 -> 0.75 | G6: ='8_6'!C19 -> 0.95828009 | H6: ='8_7'!C16 -> 0.45700656
A7: S̅ , деталей | C7: ='8_2'!C25 -> 0.83333333 | D7: ='8_4'!C21 -> 1.6342868 | E7: ='8_3'!C18 -> 0.096666034 | F7: ='8_5'!C25 -> 0.75 | G7: ='8_6'!C21 -> 1.9165602 | H7: ='8_7'!C18 -> 0.45700656
A8: 𝑞̅ , деталей | C8: ='8_2'!C24 -> 2.3148148 | D8: ='8_4'!C20 -> 1.603348 | E8: ='8_3'!C17 -> 0.0051721304 | F8: ='8_5'!C24 -> 1.40625 | G8: ='8_6'!C20 -> 3.1114185 | H8: ='8_7'!C17 -> 0.19231816
A9: k, деталей | C9: ='8_2'!C26 -> 3.1481481 | D9: ='8_4'!C22 -> 3.2376348 | E9: ='8_3'!C19 -> 0.10183816 | F9: ='8_5'!C26 -> 2.15625 | G9: ='8_6'!C22 -> 5.0279786 | H9: ='8_7'!C19 -> 0.64932472
A10: 𝛾, дет/мин | C10: ='8_2'!C29 -> 0.16666667 | D10: ='8_4'!C25 -> 0.13619057 | E10: ='8_3'!C22 -> 0.013809433 | F10: ='8_5'!C29 -> 0.25 | G10: ='8_6'!C25 -> 0.15971335 | H10: ='8_7'!C22 -> 0.065286652
A11: 𝑤̅, мин | C11: ='8_2'!C27 -> 13.888889 | D11: ='8_4'!C23 -> 11.772827 | E11: ='8_3'!C20 -> 0.37453603 | F11: ='8_5'!C27 -> 5.625 | G11: ='8_6'!C23 -> 19.481268 | H11: ='8_7'!C20 -> 2.9457501
A12: 𝑡̅, мин | C12: ='8_2'!C28 -> 18.888889 | D12: ='8_4'!C24 -> 23.772827 | E12: ='8_3'!C21 -> 7.374536 | F12: ='8_5'!C28 -> 8.625 | G12: ='8_6'!C24 -> 31.481268 | H12: ='8_7'!C21 -> 9.9457501
A13: Вероятность отсутствия очереди B1-B2 | C13: ='8_4'!C27 -> 0.26947289 | F13: ='8_6'!C27 -> 0.065686667
A14: Прибыль | C14: ='8_10'!E22 -> 547.65706 | F14: ='8_8'!E22 -> 1008.2752

Sheet 8_10
A1: Найти прибыль от работы участка за 8 часов (8.6, 8.7, 8.9)
A3: Выручка от обслуживания заявок в течении времени Т:
A4: V = γ*C*T=V(A)+V(B1-B2)+V(C)= | E4: =B15*B16*480+C15*C16*480+D15*D16*480 -> 1984
A5: Затраты связанные собслуживанием заявок в канале в в течение времени Т:
A6: Zобсл = γ* Cобсл* T= | E6: =B15*B17*480+C15*C17*480+D15*D17*480 -> 736
A7: Затраты, связанные с эксплуатацией канала в течение времени T:
A8: Zэксп = ( S̅ * Cраб + (m - S̅ ) *Cпр )*T= | E8: =(B19*B11+(B20-B19)*B12)*B18+(C19*C11+(C20-C19)*C12)*B18+(D19*D11+(D20-D19)*D12)*B18 -> 700.34294
B10: A | C10: B | D10: C
A11: Работа | B11: 0.3 | C11: 0.6 | D11: 0.5
A12: Простой | B12: 0.1 | C12: 0.2 | D12: 0.1
A13: Прочие расходы, связанные с выпуском деталей типа 1 и 2, составляют 2 и 8 д.е. соответственно. Детали типа 1 продаются по цене 5 д.е., типа 2 - 22 д.е.
A15: γ | B15: ='8_2'!C29 -> 0.16666667 | C15: ='8_4'!C25 -> 0.13619057 | D15: ='8_3'!C22 -> 0.013809433
A16: Выручка | B16: 5 | C16: 22 | D16: 22
A17: Прочие | B17: 2 | C17: 8 | D17: 8
A18: Т, мин | B18: 480
A19: S̅ | B19: ='8_2'!C25 -> 0.83333333 | C19: ='8_4'!C21 -> 1.6342868 | D19: ='8_3'!C18 -> 0.096666034
A20: m | B20: 1 | C20: 2 | D20: 1
A22: Общая прибль: | C22: V - Zобсл - Zэксп = | E22: =E4-E6-E8 -> 547.65706
